[{"public_metrics":{"retweet_count":0,"reply_count":0,"like_count":0,"quote_count":0},"text":"Game day @ModaCenter ! #RipCity \n\nhttps://t.co/UTOQrvH6Qx 👈\n\n@trailblazers @TrailBlazersPR @blazersedge @Dame_Lillard @CJMcCollum @bosnianbeast27 @farouq1 @ShabazzNapier @BlazersFr https://t.co/6wZcxPQM0J","lang":"en","conversation_id":"954783091406573569","created_at":"2018-01-20T18:30:02.000Z","context_annotations":[{"domain":{"id":"3","name":"TV Shows","description":"Television shows from around the world"},"entity":{"id":"10029190505","name":"Live: NBA Basketball","description":"Live coverage from the National Basketball Association, the top basketball league in North America."}},{"domain":{"id":"3","name":"TV Shows","description":"Television shows from around the world"},"entity":{"id":"10029304530","name":"NBA Basketball"}},{"domain":{"id":"10","name":"Person","description":"Named people in the world like Nelson Mandela"},"entity":{"id":"809849113395150848","name":"Damian Lillard"}},{"domain":{"id":"10","name":"Person","description":"Named people in the world like Nelson Mandela"},"entity":{"id":"809849113395150850","name":"Al-Farouq Aminu"}},{"domain":{"id":"60","name":"Athlete","description":"An athlete in the world, like Serena Williams or Lionel Messi"},"entity":{"id":"809849113395150848","name":"Damian Lillard"}},{"domain":{"id":"60","name":"Athlete","description":"An athlete in the world, like Serena Williams or Lionel Messi"},"entity":{"id":"809849113395150850","name":"Al-Farouq Aminu"}},{"domain":{"id":"10","name":"Person","description":"Named people in the world like Nelson Mandela"},"entity":{"id":"809849112568819712","name":"Shabazz Napier"}},{"domain":{"id":"10","name":"Person","description":"Named people in the world like Nelson Mandela"},"entity":{"id":"809849118424076288","name":"CJ McCollum"}},{"domain":{"id":"12","name":"Sports Team","description":"A sports team organization, like Arsenal and the Boston Celtics"},"entity":{"id":"706083863278137344","name":"Portland Trail Blazers"}},{"domain":{"id":"26","name":"Sports League","description":""},"entity":{"id":"706083889454813185","name":"NBA"}},{"domain":{"id":"60","name":"Athlete","description":"An athlete in the world, like Serena Williams or Lionel Messi"},"entity":{"id":"809849112568819712","name":"Shabazz Napier"}},{"domain":{"id":"60","name":"Athlete","description":"An athlete in the world, like Serena Williams or Lionel Messi"},"entity":{"id":"809849118424076288","name":"CJ McCollum"}}],"entities":{"hashtags":[{"start":23,"end":31,"tag":"RipCity"}],"urls":[{"start":34,"end":57,"url":"https://t.co/UTOQrvH6Qx","expanded_url":"http://winwin-store.com/","display_url":"winwin-store.com","status":200,"unwound_url":"http://winwin-store.com/"},{"start":181,"end":204,"url":"https://t.co/6wZcxPQM0J","expanded_url":"https://twitter.com/LKVids/status/954783091406573569/photo/1","display_url":"pic.twitter.com/6wZcxPQM0J"}],"mentions":[{"start":9,"end":20,"username":"ModaCenter"},{"start":61,"end":74,"username":"trailblazers"},{"start":75,"end":90,"username":"TrailBlazersPR"},{"start":91,"end":103,"username":"blazersedge"},{"start":104,"end":117,"username":"Dame_Lillard"},{"start":118,"end":129,"username":"CJMcCollum"},{"start":130,"end":145,"username":"bosnianbeast27"},{"start":146,"end":154,"username":"farouq1"},{"start":155,"end":169,"username":"ShabazzNapier"},{"start":170,"end":180,"username":"BlazersFr"}],"annotations":{}},"author_id":"936597959193649152","attachments":{"media_keys":["3_954776605808910336"]},"source":"Twitter Web Client","id":"954783091406573569","possibly_sensitive":false,"referenced_tweets":{},"geo":{},"Player":"farouq1","DateTime":"2018-01-20 22:00:00","GameId":"201801200POR"},{"public_metrics":{"retweet_count":0,"reply_count":0,"like_count":1,"quote_count":0},"text":"Congrats Blazers! https://t.co/UgULfaVv2v","lang":"en","conversation_id":"954542580313804801","created_at":"2018-01-20T02:34:20.000Z","context_annotations":[{"domain":{"id":"3","name":"TV Shows","description":"Television shows from around the world"},"entity":{"id":"10029190505","name":"Live: NBA Basketball","description":"Live coverage from the National Basketball Association, the top basketball league in North America."}},{"domain":{"id":"3","name":"TV Shows","description":"Television shows from around the world"},"entity":{"id":"10029304530","name":"NBA Basketball"}},{"domain":{"id":"12","name":"Sports Team","description":"A sports team organization, like Arsenal and the Boston Celtics"},"entity":{"id":"706083863278137344","name":"Portland Trail Blazers"}},{"domain":{"id":"26","name":"Sports League","description":""},"entity":{"id":"706083889454813185","name":"NBA"}}],"entities":{"hashtags":{},"urls":[{"start":18,"end":41,"url":"https://t.co/UgULfaVv2v","expanded_url":"https://twitter.com/farouq1/status/954229864751681536","display_url":"twitter.com/farouq1/status…"}],"mentions":{},"annotations":[{"start":9,"end":15,"probability":0.782,"type":"Organization","normalized_text":"Blazers"}]},"author_id":"590985203","attachments":{"media_keys":{}},"source":"Twitter for iPhone","id":"954542580313804801","possibly_sensitive":false,"referenced_tweets":[{"type":"quoted","id":"954229864751681536"}],"geo":{"place_id":"7142eb97ae21e839"},"Player":"farouq1","DateTime":"2018-01-20 22:00:00","GameId":"201801200POR"},{"public_metrics":{"retweet_count":0,"reply_count":0,"like_count":0,"quote_count":0},"text":"@TexasCoffee03 @JaxAustin @AdamRichman @darcydonavan @gilliansmunoz @JCassidyMusic @KRIS6_PTorres @TommyBo40 @StanCottenWF @ParisHilton @JillKassidyy @3mimo3 @ArianaGrande @farouq1 What’s wrong my friend?","lang":"en","conversation_id":"953810676845285376","created_at":"2018-01-20T02:05:21.000Z","context_annotations":[{"domain":{"id":"10","name":"Person","description":"Named people in the world like Nelson Mandela"},"entity":{"id":"809849113395150850","name":"Al-Farouq Aminu"}},{"domain":{"id":"60","name":"Athlete","description":"An athlete in the world, like Serena Williams or Lionel Messi"},"entity":{"id":"809849113395150850","name":"Al-Farouq Aminu"}},{"domain":{"id":"10","name":"Person","description":"Named people in the world like Nelson Mandela"},"entity":{"id":"806557506851848192","name":"Ariana Grande","description":"Ariana Grande"}},{"domain":{"id":"10","name":"Person","description":"Named people in the world like Nelson Mandela"},"entity":{"id":"808720282332450816","name":"Paris Hilton","description":"Paris Hilton"}},{"domain":{"id":"10","name":"Person","description":"Named people in the world like Nelson Mandela"},"entity":{"id":"877222964659232768","name":"Tommy Bohanon","description":"Tommy Bohanon"}},{"domain":{"id":"54","name":"Musician","description":"A musician in the world, like Adele or Bob Dylan"},"entity":{"id":"806557506851848192","name":"Ariana Grande","description":"Ariana Grande"}},{"domain":{"id":"58","name":"Entertainment Personality","description":"An entertainment personality in the world, like Anderson Cooper or Miranda Sings"},"entity":{"id":"808720282332450816","name":"Paris Hilton","description":"Paris Hilton"}},{"domain":{"id":"60","name":"Athlete","description":"An athlete in the world, like Serena Williams or Lionel Messi"},"entity":{"id":"877222964659232768","name":"Tommy Bohanon","description":"Tommy Bohanon"}}],"entities":{"hashtags":{},"urls":{},"mentions":[{"start":0,"end":14,"username":"TexasCoffee03"},{"start":15,"end":25,"username":"JaxAustin"},{"start":26,"end":38,"username":"AdamRichman"},{"start":39,"end":52,"username":"darcydonavan"},{"start":68,"end":82,"username":"JCassidyMusic"},{"start":98,"end":108,"username":"TommyBo40"},{"start":109,"end":122,"username":"StanCottenWF"},{"start":123,"end":135,"username":"ParisHilton"},{"start":136,"end":149,"username":"JillKassidyy"},{"start":150,"end":157,"username":"3mimo3"},{"start":158,"end":171,"username":"ArianaGrande"},{"start":172,"end":180,"username":"farouq1"}],"annotations":{}},"author_id":"157365725","attachments":{"media_keys":{}},"source":"Twitter for iPhone","id":"954535285445951488","possibly_sensitive":false,"referenced_tweets":[{"type":"replied_to","id":"953810676845285376"}],"geo":{},"in_reply_to_user_id":"1327436137","Player":"farouq1","DateTime":"2018-01-20 22:00:00","GameId":"201801200POR"},{"public_metrics":{"retweet_count":0,"reply_count":0,"like_count":0,"quote_count":0},"text":"@farouq1 WHAT A GREAT GAME!!  I LOVE MY BLAZERS!!🏀❤️","lang":"en","conversation_id":"954229864751681536","created_at":"2018-01-19T13:45:29.000Z","context_annotations":[{"domain":{"id":"10","name":"Person","description":"Named people in the world like Nelson Mandela"},"entity":{"id":"809849113395150850","name":"Al-Farouq Aminu"}},{"domain":{"id":"60","name":"Athlete","description":"An athlete in the world, like Serena Williams or Lionel Messi"},"entity":{"id":"809849113395150850","name":"Al-Farouq Aminu"}}],"entities":{"hashtags":{},"urls":{},"mentions":[{"start":0,"end":8,"username":"farouq1"}],"annotations":[{"start":40,"end":46,"probability":0.8368,"type":"Organization","normalized_text":"BLAZERS"}]},"author_id":"520935005","attachments":{"media_keys":{}},"source":"Twitter for iPhone","id":"954349092078931968","possibly_sensitive":false,"referenced_tweets":[{"type":"replied_to","id":"954229864751681536"}],"geo":{},"in_reply_to_user_id":"76809678","Player":"farouq1","DateTime":"2018-01-20 22:00:00","GameId":"201801200POR"},{"public_metrics":{"retweet_count":0,"reply_count":0,"like_count":0,"quote_count":0},"text":"@farouq1 Thanks for the autographed T Chief!","lang":"en","conversation_id":"954229864751681536","created_at":"2018-01-19T06:28:46.000Z","context_annotations":[{"domain":{"id":"10","name":"Person","description":"Named people in the world like Nelson Mandela"},"entity":{"id":"809849113395150850","name":"Al-Farouq Aminu"}},{"domain":{"id":"60","name":"Athlete","description":"An athlete in the world, like Serena Williams or Lionel Messi"},"entity":{"id":"809849113395150850","name":"Al-Farouq Aminu"}}],"entities":{"hashtags":{},"urls":{},"mentions":[{"start":0,"end":8,"username":"farouq1"}],"annotations":{}},"author_id":"117847658","attachments":{"media_keys":{}},"source":"Twitter for iPhone","id":"954239189704310786","possibly_sensitive":false,"referenced_tweets":[{"type":"replied_to","id":"954229864751681536"}],"geo":{},"in_reply_to_user_id":"76809678","Player":"farouq1","DateTime":"2018-01-20 22:00:00","GameId":"201801200POR"},{"public_metrics":{"retweet_count":5,"reply_count":0,"like_count":17,"quote_count":0},"text":"Blazers 100, Pacers 86: FINAL. 26 points, 8 assists, 5 rebounds for @Dame_Lillard. 19 points, 17 rebounds for @bosnianbeast27. 16 points, 3 rebounds for @CJMcCollum. 13 points for @ShabazzNapier, 12 points, 9 rebounds for @farouq1.","lang":"en","conversation_id":"954219849978228737","created_at":"2018-01-19T05:11:55.000Z","context_annotations":[{"domain":{"id":"3","name":"TV Shows","description":"Television shows from around the world"},"entity":{"id":"10000607734","name":"NBA Basketball","description":"All the latest basketball action from the NBA."}},{"domain":{"id":"3","name":"TV Shows","description":"Television shows from around the world"},"entity":{"id":"10029190505","name":"Live: NBA Basketball","description":"Live coverage from the National Basketball Association, the top basketball league in North America."}},{"domain":{"id":"3","name":"TV Shows","description":"Television shows from around the world"},"entity":{"id":"10029304530","name":"NBA Basketball"}},{"domain":{"id":"6","name":"Sports Event"},"entity":{"id":"903408373495865344","name":"Pacers at Trail Blazers"}},{"domain":{"id":"10","name":"Person","description":"Named people in the world like Nelson Mandela"},"entity":{"id":"809849113395150848","name":"Damian Lillard"}},{"domain":{"id":"10","name":"Person","description":"Named people in the world like Nelson Mandela"},"entity":{"id":"809849113395150850","name":"Al-Farouq Aminu"}},{"domain":{"id":"12","name":"Sports Team","description":"A sports team organization, like Arsenal and the Boston Celtics"},"entity":{"id":"706083862846132224","name":"Indiana Pacers"}},{"domain":{"id":"26","name":"Sports League","description":""},"entity":{"id":"706083889454813185","name":"NBA"}},{"domain":{"id":"39","name":"Basketball Game","description":"Sports Event specific to Basketball games"},"entity":{"id":"903408373495865344","name":"Pacers at Trail Blazers"}},{"domain":{"id":"60","name":"Athlete","description":"An athlete in the world, like Serena Williams or Lionel Messi"},"entity":{"id":"809849113395150848","name":"Damian Lillard"}},{"domain":{"id":"60","name":"Athlete","description":"An athlete in the world, like Serena Williams or Lionel Messi"},"entity":{"id":"809849113395150850","name":"Al-Farouq Aminu"}},{"domain":{"id":"10","name":"Person","description":"Named people in the world like Nelson Mandela"},"entity":{"id":"809849112568819712","name":"Shabazz Napier"}},{"domain":{"id":"10","name":"Person","description":"Named people in the world like Nelson Mandela"},"entity":{"id":"809849118424076288","name":"CJ McCollum"}},{"domain":{"id":"60","name":"Athlete","description":"An athlete in the world, like Serena Williams or Lionel Messi"},"entity":{"id":"809849112568819712","name":"Shabazz Napier"}},{"domain":{"id":"60","name":"Athlete","description":"An athlete in the world, like Serena Williams or Lionel Messi"},"entity":{"id":"809849118424076288","name":"CJ McCollum"}},{"domain":{"id":"39","name":"Basketball Game","description":"Sports Event specific to Basketball games"},"entity":{"id":"903408373495865344","name":"Pacers at Trail Blazers"}}],"entities":{"hashtags":{},"urls":{},"mentions":[{"start":68,"end":81,"username":"Dame_Lillard"},{"start":110,"end":125,"username":"bosnianbeast27"},{"start":153,"end":164,"username":"CJMcCollum"},{"start":180,"end":194,"username":"ShabazzNapier"},{"start":222,"end":230,"username":"farouq1"}],"annotations":[{"start":0,"end":6,"probability":0.9544,"type":"Organization","normalized_text":"Blazers"},{"start":13,"end":18,"probability":0.9639,"type":"Organization","normalized_text":"Pacers"}]},"author_id":"14328072","attachments":{"media_keys":{}},"source":"Twitter Web Client","id":"954219849978228737","possibly_sensitive":false,"referenced_tweets":{},"geo":{},"Player":"farouq1","DateTime":"2018-01-20 22:00:00","GameId":"201801200POR"},{"public_metrics":{"retweet_count":0,"reply_count":0,"like_count":0,"quote_count":0},"text":"@CHold @ShabazzNapier @bosnianbeast27 @Dame_Lillard @CJMcCollum @farouq1 Max Contract Napier ASAP","lang":"en","conversation_id":"954211279152934912","created_at":"2018-01-19T04:38:33.000Z","context_annotations":[{"domain":{"id":"6","name":"Sports Event"},"entity":{"id":"903408373495865344","name":"Pacers at Trail Blazers"}},{"domain":{"id":"10","name":"Person","description":"Named people in the world like Nelson Mandela"},"entity":{"id":"809849113395150848","name":"Damian Lillard"}},{"domain":{"id":"10","name":"Person","description":"Named people in the world like Nelson Mandela"},"entity":{"id":"809849113395150850","name":"Al-Farouq Aminu"}},{"domain":{"id":"26","name":"Sports League","description":""},"entity":{"id":"706083889454813185","name":"NBA"}},{"domain":{"id":"39","name":"Basketball Game","description":"Sports Event specific to Basketball games"},"entity":{"id":"903408373495865344","name":"Pacers at Trail Blazers"}},{"domain":{"id":"60","name":"Athlete","description":"An athlete in the world, like Serena Williams or Lionel Messi"},"entity":{"id":"809849113395150848","name":"Damian Lillard"}},{"domain":{"id":"60","name":"Athlete","description":"An athlete in the world, like Serena Williams or Lionel Messi"},"entity":{"id":"809849113395150850","name":"Al-Farouq Aminu"}},{"domain":{"id":"10","name":"Person","description":"Named people in the world like Nelson Mandela"},"entity":{"id":"809849112568819712","name":"Shabazz Napier"}},{"domain":{"id":"10","name":"Person","description":"Named people in the world like Nelson Mandela"},"entity":{"id":"809849118424076288","name":"CJ McCollum"}},{"domain":{"id":"60","name":"Athlete","description":"An athlete in the world, like Serena Williams or Lionel Messi"},"entity":{"id":"809849112568819712","name":"Shabazz Napier"}},{"domain":{"id":"60","name":"Athlete","description":"An athlete in the world, like Serena Williams or Lionel Messi"},"entity":{"id":"809849118424076288","name":"CJ McCollum"}}],"entities":{"hashtags":{},"urls":{},"mentions":[{"start":0,"end":6,"username":"CHold"},{"start":7,"end":21,"username":"ShabazzNapier"},{"start":22,"end":37,"username":"bosnianbeast27"},{"start":38,"end":51,"username":"Dame_Lillard"},{"start":52,"end":63,"username":"CJMcCollum"},{"start":64,"end":72,"username":"farouq1"}],"annotations":[{"start":73,"end":91,"probability":0.3405,"type":"Person","normalized_text":"Max Contract Napier"}]},"author_id":"3067776431","attachments":{"media_keys":{}},"source":"Twitter for iPad","id":"954211451991883776","possibly_sensitive":false,"referenced_tweets":[{"type":"replied_to","id":"954211279152934912"}],"geo":{},"in_reply_to_user_id":"14328072","Player":"farouq1","DateTime":"2018-01-20 22:00:00","GameId":"201801200POR"},{"public_metrics":{"retweet_count":1,"reply_count":1,"like_count":9,"quote_count":0},"text":"Blazers 74, Pacers 74: end of third quarter. @ShabazzNapier's steal/three at the buzzer ties the game up going into the fourth. 16 points, 16 rebounds for @bosnianbeast27. 13 points each for @Dame_Lillard/@CJMcCollum. 12 points, 7 rebounds for @farouq1.","lang":"en","conversation_id":"954211279152934912","created_at":"2018-01-19T04:37:51.000Z","context_annotations":[{"domain":{"id":"3","name":"TV Shows","description":"Television shows from around the world"},"entity":{"id":"10000607734","name":"NBA Basketball","description":"All the latest basketball action from the NBA."}},{"domain":{"id":"3","name":"TV Shows","description":"Television shows from around the world"},"entity":{"id":"10029190505","name":"Live: NBA Basketball","description":"Live coverage from the National Basketball Association, the top basketball league in North America."}},{"domain":{"id":"3","name":"TV Shows","description":"Television shows from around the world"},"entity":{"id":"10029304530","name":"NBA Basketball"}},{"domain":{"id":"6","name":"Sports Event"},"entity":{"id":"903408373495865344","name":"Pacers at Trail Blazers"}},{"domain":{"id":"10","name":"Person","description":"Named people in the world like Nelson Mandela"},"entity":{"id":"809849113395150848","name":"Damian Lillard"}},{"domain":{"id":"10","name":"Person","description":"Named people in the world like Nelson Mandela"},"entity":{"id":"809849113395150850","name":"Al-Farouq Aminu"}},{"domain":{"id":"12","name":"Sports Team","description":"A sports team organization, like Arsenal and the Boston Celtics"},"entity":{"id":"706083862846132224","name":"Indiana Pacers"}},{"domain":{"id":"26","name":"Sports League","description":""},"entity":{"id":"706083889454813185","name":"NBA"}},{"domain":{"id":"39","name":"Basketball Game","description":"Sports Event specific to Basketball games"},"entity":{"id":"903408373495865344","name":"Pacers at Trail Blazers"}},{"domain":{"id":"60","name":"Athlete","description":"An athlete in the world, like Serena Williams or Lionel Messi"},"entity":{"id":"809849113395150848","name":"Damian Lillard"}},{"domain":{"id":"60","name":"Athlete","description":"An athlete in the world, like Serena Williams or Lionel Messi"},"entity":{"id":"809849113395150850","name":"Al-Farouq Aminu"}},{"domain":{"id":"10","name":"Person","description":"Named people in the world like Nelson Mandela"},"entity":{"id":"809849112568819712","name":"Shabazz Napier"}},{"domain":{"id":"10","name":"Person","description":"Named people in the world like Nelson Mandela"},"entity":{"id":"809849118424076288","name":"CJ McCollum"}},{"domain":{"id":"60","name":"Athlete","description":"An athlete in the world, like Serena Williams or Lionel Messi"},"entity":{"id":"809849112568819712","name":"Shabazz Napier"}},{"domain":{"id":"60","name":"Athlete","description":"An athlete in the world, like Serena Williams or Lionel Messi"},"entity":{"id":"809849118424076288","name":"CJ McCollum"}},{"domain":{"id":"39","name":"Basketball Game","description":"Sports Event specific to Basketball games"},"entity":{"id":"903408373495865344","name":"Pacers at Trail Blazers"}}],"entities":{"hashtags":{},"urls":{},"mentions":[{"start":45,"end":59,"username":"ShabazzNapier"},{"start":155,"end":170,"username":"bosnianbeast27"},{"start":191,"end":204,"username":"Dame_Lillard"},{"start":205,"end":216,"username":"CJMcCollum"},{"start":244,"end":252,"username":"farouq1"}],"annotations":[{"start":0,"end":6,"probability":0.9718,"type":"Organization","normalized_text":"Blazers"},{"start":12,"end":17,"probability":0.951,"type":"Organization","normalized_text":"Pacers"}]},"author_id":"14328072","attachments":{"media_keys":{}},"source":"Twitter Web Client","id":"954211279152934912","possibly_sensitive":false,"referenced_tweets":{},"geo":{},"Player":"farouq1","DateTime":"2018-01-20 22:00:00","GameId":"201801200POR"},{"public_metrics":{"retweet_count":0,"reply_count":0,"like_count":0,"quote_count":0},"text":"@CHold @bosnianbeast27 @farouq1 @Dame_Lillard @CJMcCollum I really can't remember, mavbe I am false, but on blazers broadcast they also said that","lang":"en","conversation_id":"954202317057765378","created_at":"2018-01-19T04:28:02.000Z","context_annotations":[{"domain":{"id":"6","name":"Sports Event"},"entity":{"id":"903408373495865344","name":"Pacers at Trail Blazers"}},{"domain":{"id":"10","name":"Person","description":"Named people in the world like Nelson Mandela"},"entity":{"id":"809849113395150848","name":"Damian Lillard"}},{"domain":{"id":"10","name":"Person","description":"Named people in the world like Nelson Mandela"},"entity":{"id":"809849113395150850","name":"Al-Farouq Aminu"}},{"domain":{"id":"26","name":"Sports League","description":""},"entity":{"id":"706083889454813185","name":"NBA"}},{"domain":{"id":"39","name":"Basketball Game","description":"Sports Event specific to Basketball games"},"entity":{"id":"903408373495865344","name":"Pacers at Trail Blazers"}},{"domain":{"id":"60","name":"Athlete","description":"An athlete in the world, like Serena Williams or Lionel Messi"},"entity":{"id":"809849113395150848","name":"Damian Lillard"}},{"domain":{"id":"60","name":"Athlete","description":"An athlete in the world, like Serena Williams or Lionel Messi"},"entity":{"id":"809849113395150850","name":"Al-Farouq Aminu"}},{"domain":{"id":"10","name":"Person","description":"Named people in the world like Nelson Mandela"},"entity":{"id":"809849118424076288","name":"CJ McCollum"}},{"domain":{"id":"60","name":"Athlete","description":"An athlete in the world, like Serena Williams or Lionel Messi"},"entity":{"id":"809849118424076288","name":"CJ McCollum"}}],"entities":{"hashtags":{},"urls":{},"mentions":[{"start":0,"end":6,"username":"CHold"},{"start":7,"end":22,"username":"bosnianbeast27"},{"start":23,"end":31,"username":"farouq1"},{"start":32,"end":45,"username":"Dame_Lillard"},{"start":46,"end":57,"username":"CJMcCollum"}],"annotations":[{"start":108,"end":114,"probability":0.6798,"type":"Organization","normalized_text":"blazers"}]},"author_id":"3646314738","attachments":{"media_keys":{}},"source":"Twitter for Android","id":"954208806128504832","possibly_sensitive":false,"referenced_tweets":[{"type":"replied_to","id":"954207250716901376"}],"geo":{},"in_reply_to_user_id":"14328072","Player":"farouq1","DateTime":"2018-01-20 22:00:00","GameId":"201801200POR"},{"public_metrics":{"retweet_count":1,"reply_count":0,"like_count":16,"quote_count":0},"text":"What I like most about @farouq1's three-point shots is how they disappear off the top of my television screen before reappearing and dropping meteor-like into the basket. #nothingbutnet #RipCity","lang":"en","conversation_id":"954207528899899392","created_at":"2018-01-19T04:22:57.000Z","context_annotations":[{"domain":{"id":"3","name":"TV Shows","description":"Television shows from around the world"},"entity":{"id":"10029190505","name":"Live: NBA Basketball","description":"Live coverage from the National Basketball Association, the top basketball league in North America."}},{"domain":{"id":"3","name":"TV Shows","description":"Television shows from around the world"},"entity":{"id":"10029304530","name":"NBA Basketball"}},{"domain":{"id":"6","name":"Sports Event"},"entity":{"id":"903408373495865344","name":"Pacers at Trail Blazers"}},{"domain":{"id":"10","name":"Person","description":"Named people in the world like Nelson Mandela"},"entity":{"id":"809849113395150850","name":"Al-Farouq Aminu"}},{"domain":{"id":"26","name":"Sports League","description":""},"entity":{"id":"706083889454813185","name":"NBA"}},{"domain":{"id":"39","name":"Basketball Game","description":"Sports Event specific to Basketball games"},"entity":{"id":"903408373495865344","name":"Pacers at Trail Blazers"}},{"domain":{"id":"60","name":"Athlete","description":"An athlete in the world, like Serena Williams or Lionel Messi"},"entity":{"id":"809849113395150850","name":"Al-Farouq Aminu"}},{"domain":{"id":"12","name":"Sports Team","description":"A sports team organization, like Arsenal and the Boston Celtics"},"entity":{"id":"706083863278137344","name":"Portland Trail Blazers"}},{"domain":{"id":"26","name":"Sports League","description":""},"entity":{"id":"706083889454813185","name":"NBA"}}],"entities":{"hashtags":[{"start":171,"end":185,"tag":"nothingbutnet"},{"start":186,"end":194,"tag":"RipCity"}],"urls":{},"mentions":[{"start":23,"end":31,"username":"farouq1"}],"annotations":{}},"author_id":"27474321","attachments":{"media_keys":{}},"source":"Twitter Web Client","id":"954207528899899392","possibly_sensitive":false,"referenced_tweets":{},"geo":{},"Player":"farouq1","DateTime":"2018-01-20 22:00:00","GameId":"201801200POR"},{"public_metrics":{"retweet_count":0,"reply_count":1,"like_count":0,"quote_count":0},"text":"@muris_jasarevic @bosnianbeast27 @farouq1 @Dame_Lillard @CJMcCollum Our stats people say that's a double-double in ANY half. They still claim it's his first first half double-double.","lang":"en","conversation_id":"954202317057765378","created_at":"2018-01-19T04:21:51.000Z","context_annotations":[{"domain":{"id":"6","name":"Sports Event"},"entity":{"id":"903408373495865344","name":"Pacers at Trail Blazers"}},{"domain":{"id":"10","name":"Person","description":"Named people in the world like Nelson Mandela"},"entity":{"id":"809849113395150848","name":"Damian Lillard"}},{"domain":{"id":"10","name":"Person","description":"Named people in the world like Nelson Mandela"},"entity":{"id":"809849113395150850","name":"Al-Farouq Aminu"}},{"domain":{"id":"26","name":"Sports League","description":""},"entity":{"id":"706083889454813185","name":"NBA"}},{"domain":{"id":"39","name":"Basketball Game","description":"Sports Event specific to Basketball games"},"entity":{"id":"903408373495865344","name":"Pacers at Trail Blazers"}},{"domain":{"id":"60","name":"Athlete","description":"An athlete in the world, like Serena Williams or Lionel Messi"},"entity":{"id":"809849113395150848","name":"Damian Lillard"}},{"domain":{"id":"60","name":"Athlete","description":"An athlete in the world, like Serena Williams or Lionel Messi"},"entity":{"id":"809849113395150850","name":"Al-Farouq Aminu"}},{"domain":{"id":"10","name":"Person","description":"Named people in the world like Nelson Mandela"},"entity":{"id":"809849118424076288","name":"CJ McCollum"}},{"domain":{"id":"60","name":"Athlete","description":"An athlete in the world, like Serena Williams or Lionel Messi"},"entity":{"id":"809849118424076288","name":"CJ McCollum"}},{"domain":{"id":"39","name":"Basketball Game","description":"Sports Event specific to Basketball games"},"entity":{"id":"903408373495865344","name":"Pacers at Trail Blazers"}}],"entities":{"hashtags":{},"urls":{},"mentions":[{"start":0,"end":16,"username":"muris_jasarevic"},{"start":17,"end":32,"username":"bosnianbeast27"},{"start":33,"end":41,"username":"farouq1"},{"start":42,"end":55,"username":"Dame_Lillard"},{"start":56,"end":67,"username":"CJMcCollum"}],"annotations":{}},"author_id":"14328072","attachments":{"media_keys":{}},"source":"Twitter Web Client","id":"954207250716901376","possibly_sensitive":false,"referenced_tweets":[{"type":"replied_to","id":"954206222340820992"}],"geo":{},"in_reply_to_user_id":"3646314738","Player":"farouq1","DateTime":"2018-01-20 22:00:00","GameId":"201801200POR"},{"public_metrics":{"retweet_count":0,"reply_count":0,"like_count":0,"quote_count":0},"text":"@muris_jasarevic @bosnianbeast27 @farouq1 @Dame_Lillard @CJMcCollum Can you tell me games? Our stats people say that was his first career first half double double, but I'd be happy to correct them if you could point me to at least one of those games.","lang":"en","conversation_id":"954202317057765378","created_at":"2018-01-19T04:18:30.000Z","context_annotations":[{"domain":{"id":"6","name":"Sports Event"},"entity":{"id":"903408373495865344","name":"Pacers at Trail Blazers"}},{"domain":{"id":"10","name":"Person","description":"Named people in the world like Nelson Mandela"},"entity":{"id":"809849113395150848","name":"Damian Lillard"}},{"domain":{"id":"10","name":"Person","description":"Named people in the world like Nelson Mandela"},"entity":{"id":"809849113395150850","name":"Al-Farouq Aminu"}},{"domain":{"id":"26","name":"Sports League","description":""},"entity":{"id":"706083889454813185","name":"NBA"}},{"domain":{"id":"39","name":"Basketball Game","description":"Sports Event specific to Basketball games"},"entity":{"id":"903408373495865344","name":"Pacers at Trail Blazers"}},{"domain":{"id":"60","name":"Athlete","description":"An athlete in the world, like Serena Williams or Lionel Messi"},"entity":{"id":"809849113395150848","name":"Damian Lillard"}},{"domain":{"id":"60","name":"Athlete","description":"An athlete in the world, like Serena Williams or Lionel Messi"},"entity":{"id":"809849113395150850","name":"Al-Farouq Aminu"}},{"domain":{"id":"10","name":"Person","description":"Named people in the world like Nelson Mandela"},"entity":{"id":"809849118424076288","name":"CJ McCollum"}},{"domain":{"id":"60","name":"Athlete","description":"An athlete in the world, like Serena Williams or Lionel Messi"},"entity":{"id":"809849118424076288","name":"CJ McCollum"}},{"domain":{"id":"39","name":"Basketball Game","description":"Sports Event specific to Basketball games"},"entity":{"id":"903408373495865344","name":"Pacers at Trail Blazers"}}],"entities":{"hashtags":{},"urls":{},"mentions":[{"start":0,"end":16,"username":"muris_jasarevic"},{"start":17,"end":32,"username":"bosnianbeast27"},{"start":33,"end":41,"username":"farouq1"},{"start":42,"end":55,"username":"Dame_Lillard"},{"start":56,"end":67,"username":"CJMcCollum"}],"annotations":{}},"author_id":"14328072","attachments":{"media_keys":{}},"source":"Twitter Web Client","id":"954206405581422593","possibly_sensitive":false,"referenced_tweets":[{"type":"replied_to","id":"954205914965344257"}],"geo":{},"in_reply_to_user_id":"3646314738","Player":"farouq1","DateTime":"2018-01-20 22:00:00","GameId":"201801200POR"},{"public_metrics":{"retweet_count":0,"reply_count":2,"like_count":0,"quote_count":0},"text":"@muris_jasarevic @bosnianbeast27 @farouq1 @Dame_Lillard @CJMcCollum In the first half?","lang":"en","conversation_id":"954202317057765378","created_at":"2018-01-19T04:15:07.000Z","context_annotations":[{"domain":{"id":"6","name":"Sports Event"},"entity":{"id":"903408373495865344","name":"Pacers at Trail Blazers"}},{"domain":{"id":"10","name":"Person","description":"Named people in the world like Nelson Mandela"},"entity":{"id":"809849113395150848","name":"Damian Lillard"}},{"domain":{"id":"10","name":"Person","description":"Named people in the world like Nelson Mandela"},"entity":{"id":"809849113395150850","name":"Al-Farouq Aminu"}},{"domain":{"id":"26","name":"Sports League","description":""},"entity":{"id":"706083889454813185","name":"NBA"}},{"domain":{"id":"39","name":"Basketball Game","description":"Sports Event specific to Basketball games"},"entity":{"id":"903408373495865344","name":"Pacers at Trail Blazers"}},{"domain":{"id":"60","name":"Athlete","description":"An athlete in the world, like Serena Williams or Lionel Messi"},"entity":{"id":"809849113395150848","name":"Damian Lillard"}},{"domain":{"id":"60","name":"Athlete","description":"An athlete in the world, like Serena Williams or Lionel Messi"},"entity":{"id":"809849113395150850","name":"Al-Farouq Aminu"}},{"domain":{"id":"10","name":"Person","description":"Named people in the world like Nelson Mandela"},"entity":{"id":"809849118424076288","name":"CJ McCollum"}},{"domain":{"id":"60","name":"Athlete","description":"An athlete in the world, like Serena Williams or Lionel Messi"},"entity":{"id":"809849118424076288","name":"CJ McCollum"}},{"domain":{"id":"39","name":"Basketball Game","description":"Sports Event specific to Basketball games"},"entity":{"id":"903408373495865344","name":"Pacers at Trail Blazers"}}],"entities":{"hashtags":{},"urls":{},"mentions":[{"start":0,"end":16,"username":"muris_jasarevic"},{"start":17,"end":32,"username":"bosnianbeast27"},{"start":33,"end":41,"username":"farouq1"},{"start":42,"end":55,"username":"Dame_Lillard"},{"start":56,"end":67,"username":"CJMcCollum"}],"annotations":{}},"author_id":"14328072","attachments":{"media_keys":{}},"source":"Twitter Web Client","id":"954205555123367938","possibly_sensitive":false,"referenced_tweets":[{"type":"replied_to","id":"954203114772549632"}],"geo":{},"in_reply_to_user_id":"3646314738","Player":"farouq1","DateTime":"2018-01-20 22:00:00","GameId":"201801200POR"},{"public_metrics":{"retweet_count":0,"reply_count":1,"like_count":0,"quote_count":0},"text":"@CHold @bosnianbeast27 @farouq1 @Dame_Lillard @CJMcCollum Sorry, the third time in his career he's put a double-double, second time with the blazers...","lang":"en","conversation_id":"954202317057765378","created_at":"2018-01-19T04:05:25.000Z","context_annotations":[{"domain":{"id":"6","name":"Sports Event"},"entity":{"id":"903408373495865344","name":"Pacers at Trail Blazers"}},{"domain":{"id":"10","name":"Person","description":"Named people in the world like Nelson Mandela"},"entity":{"id":"809849113395150848","name":"Damian Lillard"}},{"domain":{"id":"10","name":"Person","description":"Named people in the world like Nelson Mandela"},"entity":{"id":"809849113395150850","name":"Al-Farouq Aminu"}},{"domain":{"id":"26","name":"Sports League","description":""},"entity":{"id":"706083889454813185","name":"NBA"}},{"domain":{"id":"39","name":"Basketball Game","description":"Sports Event specific to Basketball games"},"entity":{"id":"903408373495865344","name":"Pacers at Trail Blazers"}},{"domain":{"id":"60","name":"Athlete","description":"An athlete in the world, like Serena Williams or Lionel Messi"},"entity":{"id":"809849113395150848","name":"Damian Lillard"}},{"domain":{"id":"60","name":"Athlete","description":"An athlete in the world, like Serena Williams or Lionel Messi"},"entity":{"id":"809849113395150850","name":"Al-Farouq Aminu"}},{"domain":{"id":"10","name":"Person","description":"Named people in the world like Nelson Mandela"},"entity":{"id":"809849118424076288","name":"CJ McCollum"}},{"domain":{"id":"60","name":"Athlete","description":"An athlete in the world, like Serena Williams or Lionel Messi"},"entity":{"id":"809849118424076288","name":"CJ McCollum"}}],"entities":{"hashtags":{},"urls":{},"mentions":[{"start":0,"end":6,"username":"CHold"},{"start":7,"end":22,"username":"bosnianbeast27"},{"start":23,"end":31,"username":"farouq1"},{"start":32,"end":45,"username":"Dame_Lillard"},{"start":46,"end":57,"username":"CJMcCollum"}],"annotations":{}},"author_id":"3646314738","attachments":{"media_keys":{}},"source":"Twitter for Android","id":"954203114772549632","possibly_sensitive":false,"referenced_tweets":[{"type":"replied_to","id":"954202317057765378"}],"geo":{},"in_reply_to_user_id":"14328072","Player":"farouq1","DateTime":"2018-01-20 22:00:00","GameId":"201801200POR"},{"public_metrics":{"retweet_count":2,"reply_count":2,"like_count":10,"quote_count":0},"text":"Blazers 52, Pacers 47: halftime. @bosnianbeast27 with 12 points, 12 rebounds, first time in his career he's put up a double-double by halftime. 9 points, 4 rebounds for @farouq1. 8 points apiece for @Dame_Lillard and @CJMcCollum.","lang":"en","conversation_id":"954202317057765378","created_at":"2018-01-19T04:02:15.000Z","context_annotations":[{"domain":{"id":"3","name":"TV Shows","description":"Television shows from around the world"},"entity":{"id":"10000607734","name":"NBA Basketball","description":"All the latest basketball action from the NBA."}},{"domain":{"id":"3","name":"TV Shows","description":"Television shows from around the world"},"entity":{"id":"10029190505","name":"Live: NBA Basketball","description":"Live coverage from the National Basketball Association, the top basketball league in North America."}},{"domain":{"id":"3","name":"TV Shows","description":"Television shows from around the world"},"entity":{"id":"10029304530","name":"NBA Basketball"}},{"domain":{"id":"6","name":"Sports Event"},"entity":{"id":"903408373495865344","name":"Pacers at Trail Blazers"}},{"domain":{"id":"10","name":"Person","description":"Named people in the world like Nelson Mandela"},"entity":{"id":"809849113395150848","name":"Damian Lillard"}},{"domain":{"id":"10","name":"Person","description":"Named people in the world like Nelson Mandela"},"entity":{"id":"809849113395150850","name":"Al-Farouq Aminu"}},{"domain":{"id":"12","name":"Sports Team","description":"A sports team organization, like Arsenal and the Boston Celtics"},"entity":{"id":"706083862846132224","name":"Indiana Pacers"}},{"domain":{"id":"26","name":"Sports League","description":""},"entity":{"id":"706083889454813185","name":"NBA"}},{"domain":{"id":"39","name":"Basketball Game","description":"Sports Event specific to Basketball games"},"entity":{"id":"903408373495865344","name":"Pacers at Trail Blazers"}},{"domain":{"id":"60","name":"Athlete","description":"An athlete in the world, like Serena Williams or Lionel Messi"},"entity":{"id":"809849113395150848","name":"Damian Lillard"}},{"domain":{"id":"60","name":"Athlete","description":"An athlete in the world, like Serena Williams or Lionel Messi"},"entity":{"id":"809849113395150850","name":"Al-Farouq Aminu"}},{"domain":{"id":"10","name":"Person","description":"Named people in the world like Nelson Mandela"},"entity":{"id":"809849118424076288","name":"CJ McCollum"}},{"domain":{"id":"60","name":"Athlete","description":"An athlete in the world, like Serena Williams or Lionel Messi"},"entity":{"id":"809849118424076288","name":"CJ McCollum"}},{"domain":{"id":"39","name":"Basketball Game","description":"Sports Event specific to Basketball games"},"entity":{"id":"903408373495865344","name":"Pacers at Trail Blazers"}}],"entities":{"hashtags":{},"urls":{},"mentions":[{"start":33,"end":48,"username":"bosnianbeast27"},{"start":169,"end":177,"username":"farouq1"},{"start":199,"end":212,"username":"Dame_Lillard"},{"start":217,"end":228,"username":"CJMcCollum"}],"annotations":[{"start":0,"end":6,"probability":0.9724,"type":"Organization","normalized_text":"Blazers"},{"start":12,"end":17,"probability":0.9468,"type":"Organization","normalized_text":"Pacers"}]},"author_id":"14328072","attachments":{"media_keys":{}},"source":"Twitter Web Client","id":"954202317057765378","possibly_sensitive":false,"referenced_tweets":{},"geo":{},"Player":"farouq1","DateTime":"2018-01-20 22:00:00","GameId":"201801200POR"},{"public_metrics":{"retweet_count":0,"reply_count":0,"like_count":0,"quote_count":0},"text":"@trailblazers We just spent 5 minutes arguing at the TV because the jersey font makes the 3 and 6 look like 8s.  “Why are there three #8’s on the court?? Why are @CJMcCollum and @ShabazzNapier wearing @farouq1’s number?” #HorribleFont #NeedaBiggerTV","lang":"en","conversation_id":"954202223730294784","created_at":"2018-01-19T04:01:53.000Z","context_annotations":[{"domain":{"id":"3","name":"TV Shows","description":"Television shows from around the world"},"entity":{"id":"10029190505","name":"Live: NBA Basketball","description":"Live coverage from the National Basketball Association, the top basketball league in North America."}},{"domain":{"id":"3","name":"TV Shows","description":"Television shows from around the world"},"entity":{"id":"10029304530","name":"NBA Basketball"}},{"domain":{"id":"6","name":"Sports Event"},"entity":{"id":"903408373495865344","name":"Pacers at Trail Blazers"}},{"domain":{"id":"10","name":"Person","description":"Named people in the world like Nelson Mandela"},"entity":{"id":"809849113395150850","name":"Al-Farouq Aminu"}},{"domain":{"id":"26","name":"Sports League","description":""},"entity":{"id":"706083889454813185","name":"NBA"}},{"domain":{"id":"39","name":"Basketball Game","description":"Sports Event specific to Basketball games"},"entity":{"id":"903408373495865344","name":"Pacers at Trail Blazers"}},{"domain":{"id":"60","name":"Athlete","description":"An athlete in the world, like Serena Williams or Lionel Messi"},"entity":{"id":"809849113395150850","name":"Al-Farouq Aminu"}},{"domain":{"id":"10","name":"Person","description":"Named people in the world like Nelson Mandela"},"entity":{"id":"809849112568819712","name":"Shabazz Napier"}},{"domain":{"id":"10","name":"Person","description":"Named people in the world like Nelson Mandela"},"entity":{"id":"809849118424076288","name":"CJ McCollum"}},{"domain":{"id":"12","name":"Sports Team","description":"A sports team organization, like Arsenal and the Boston Celtics"},"entity":{"id":"706083863278137344","name":"Portland Trail Blazers"}},{"domain":{"id":"26","name":"Sports League","description":""},"entity":{"id":"706083889454813185","name":"NBA"}},{"domain":{"id":"60","name":"Athlete","description":"An athlete in the world, like Serena Williams or Lionel Messi"},"entity":{"id":"809849112568819712","name":"Shabazz Napier"}},{"domain":{"id":"60","name":"Athlete","description":"An athlete in the world, like Serena Williams or Lionel Messi"},"entity":{"id":"809849118424076288","name":"CJ McCollum"}}],"entities":{"hashtags":[{"start":221,"end":234,"tag":"HorribleFont"},{"start":235,"end":249,"tag":"NeedaBiggerTV"}],"urls":{},"mentions":[{"start":0,"end":13,"username":"trailblazers"},{"start":162,"end":173,"username":"CJMcCollum"},{"start":178,"end":192,"username":"ShabazzNapier"},{"start":201,"end":209,"username":"farouq1"}],"annotations":{}},"author_id":"297521665","attachments":{"media_keys":{}},"source":"Twitter for iPad","id":"954202223730294784","possibly_sensitive":false,"referenced_tweets":{},"geo":{},"in_reply_to_user_id":"6395222","Player":"farouq1","DateTime":"2018-01-20 22:00:00","GameId":"201801200POR"},{"public_metrics":{"retweet_count":0,"reply_count":0,"like_count":2,"quote_count":0},"text":"Hot start for @bosnianbeast27 and @farouq1; they're a combined 7-for-8 from the floor for a total of 17 points. #RipCity","lang":"en","conversation_id":"954193885403557888","created_at":"2018-01-19T03:28:45.000Z","context_annotations":[{"domain":{"id":"3","name":"TV Shows","description":"Television shows from around the world"},"entity":{"id":"10029190505","name":"Live: NBA Basketball","description":"Live coverage from the National Basketball Association, the top basketball league in North America."}},{"domain":{"id":"3","name":"TV Shows","description":"Television shows from around the world"},"entity":{"id":"10029304530","name":"NBA Basketball"}},{"domain":{"id":"6","name":"Sports Event"},"entity":{"id":"903408373495865344","name":"Pacers at Trail Blazers"}},{"domain":{"id":"10","name":"Person","description":"Named people in the world like Nelson Mandela"},"entity":{"id":"809849113395150850","name":"Al-Farouq Aminu"}},{"domain":{"id":"26","name":"Sports League","description":""},"entity":{"id":"706083889454813185","name":"NBA"}},{"domain":{"id":"39","name":"Basketball Game","description":"Sports Event specific to Basketball games"},"entity":{"id":"903408373495865344","name":"Pacers at Trail Blazers"}},{"domain":{"id":"60","name":"Athlete","description":"An athlete in the world, like Serena Williams or Lionel Messi"},"entity":{"id":"809849113395150850","name":"Al-Farouq Aminu"}},{"domain":{"id":"12","name":"Sports Team","description":"A sports team organization, like Arsenal and the Boston Celtics"},"entity":{"id":"706083863278137344","name":"Portland Trail Blazers"}},{"domain":{"id":"26","name":"Sports League","description":""},"entity":{"id":"706083889454813185","name":"NBA"}}],"entities":{"hashtags":[{"start":112,"end":120,"tag":"RipCity"}],"urls":{},"mentions":[{"start":14,"end":29,"username":"bosnianbeast27"},{"start":34,"end":42,"username":"farouq1"}],"annotations":{}},"author_id":"27474321","attachments":{"media_keys":{}},"source":"Twitter Web Client","id":"954193885403557888","possibly_sensitive":false,"referenced_tweets":{},"geo":{},"Player":"farouq1","DateTime":"2018-01-20 22:00:00","GameId":"201801200POR"}]
