[{"entities":{"annotations":[{"start":25,"end":36,"probability":0.9867,"type":"Person","normalized_text":"Brad Stevens"}],"mentions":[{"start":59,"end":72,"username":"danielrainge"},{"start":73,"end":89,"username":"BradStevensTeam"},{"start":90,"end":98,"username":"celtics"},{"start":99,"end":111,"username":"NBCSCeltics"},{"start":112,"end":122,"username":"jaytatum0"},{"start":123,"end":135,"username":"KyrieIrving"},{"start":136,"end":143,"username":"FCHWPO"}],"hashtags":[{"start":144,"end":157,"tag":"bradtosuitup"},{"start":158,"end":166,"tag":"celtics"}],"urls":{}},"source":"Twitter for iPhone","possibly_sensitive":false,"context_annotations":[{"domain":{"id":"3","name":"TV Shows","description":"Television shows from around the world"},"entity":{"id":"10000607734","name":"NBA Basketball","description":"All the latest basketball action from the NBA."}},{"domain":{"id":"3","name":"TV Shows","description":"Television shows from around the world"},"entity":{"id":"10029190505","name":"Live: NBA Basketball","description":"Live coverage from the National Basketball Association, the top basketball league in North America."}},{"domain":{"id":"3","name":"TV Shows","description":"Television shows from around the world"},"entity":{"id":"10029304530","name":"NBA Basketball"}},{"domain":{"id":"10","name":"Person","description":"Named people in the world like Nelson Mandela"},"entity":{"id":"809849116989669377","name":"Brad Stevens"}},{"domain":{"id":"10","name":"Person","description":"Named people in the world like Nelson Mandela"},"entity":{"id":"961675158694936576","name":"Danny Ainge","description":"Danny Ainge"}},{"domain":{"id":"12","name":"Sports Team","description":"A sports team organization, like Arsenal and the Boston Celtics"},"entity":{"id":"706083876595068928","name":"Boston Celtics"}},{"domain":{"id":"26","name":"Sports League","description":""},"entity":{"id":"706083889454813185","name":"NBA"}},{"domain":{"id":"92","name":"Sports Personality","description":"A Sports Personality like 'Skip Bayless'"},"entity":{"id":"961675158694936576","name":"Danny Ainge","description":"Danny Ainge"}},{"domain":{"id":"93","name":"Coach","description":"A Coach like 'Bill Belichick'"},"entity":{"id":"809849116989669377","name":"Brad Stevens"}},{"domain":{"id":"10","name":"Person","description":"Named people in the world like Nelson Mandela"},"entity":{"id":"809849112870809601","name":"Kyrie Irving"}},{"domain":{"id":"10","name":"Person","description":"Named people in the world like Nelson Mandela"},"entity":{"id":"809849116989632513","name":"Jaylen Brown"}},{"domain":{"id":"10","name":"Person","description":"Named people in the world like Nelson Mandela"},"entity":{"id":"831260175956783105","name":"Jayson Tatum","description":"Jayson Tatum"}},{"domain":{"id":"60","name":"Athlete","description":"An athlete in the world, like Serena Williams or Lionel Messi"},"entity":{"id":"809849112870809601","name":"Kyrie Irving"}},{"domain":{"id":"60","name":"Athlete","description":"An athlete in the world, like Serena Williams or Lionel Messi"},"entity":{"id":"809849116989632513","name":"Jaylen Brown"}},{"domain":{"id":"60","name":"Athlete","description":"An athlete in the world, like Serena Williams or Lionel Messi"},"entity":{"id":"831260175956783105","name":"Jayson Tatum","description":"Jayson Tatum"}}],"author_id":"1170147338","text":"How many retweets to get Brad Stevens to suit up and play? @danielrainge @BradStevensTeam @celtics @NBCSCeltics @jaytatum0 @KyrieIrving @FCHWPO #bradtosuitup #celtics","public_metrics":{"retweet_count":0,"reply_count":0,"like_count":0,"quote_count":0},"created_at":"2018-03-14T18:43:48.000Z","conversation_id":"973993110798651392","id":"973993110798651392","lang":"en","referenced_tweets":{},"geo":{},"attachments":{"media_keys":{}},"Player":"FCHWPO","DateTime":"2018-03-14 20:00:00","GameId":"201803140BOS"},{"entities":{"annotations":{},"mentions":[{"start":0,"end":10,"username":"halfaflip"},{"start":27,"end":41,"username":"jerome_randle"},{"start":42,"end":54,"username":"DevInTheLab"},{"start":55,"end":62,"username":"FCHWPO"},{"start":63,"end":73,"username":"YoungIvee"}],"hashtags":{},"urls":{}},"source":"Twitter for iPhone","possibly_sensitive":false,"context_annotations":[{"domain":{"id":"10","name":"Person","description":"Named people in the world like Nelson Mandela"},"entity":{"id":"809849116989632513","name":"Jaylen Brown"}},{"domain":{"id":"10","name":"Person","description":"Named people in the world like Nelson Mandela"},"entity":{"id":"840230724779229187","name":"Ivan Rabb"}},{"domain":{"id":"60","name":"Athlete","description":"An athlete in the world, like Serena Williams or Lionel Messi"},"entity":{"id":"809849116989632513","name":"Jaylen Brown"}},{"domain":{"id":"60","name":"Athlete","description":"An athlete in the world, like Serena Williams or Lionel Messi"},"entity":{"id":"840230724779229187","name":"Ivan Rabb"}}],"author_id":"242536562","text":"@halfaflip @valandrelaguna @jerome_randle @DevInTheLab @FCHWPO @YoungIvee 😂😂😂😂😂 you got it buddy","public_metrics":{"retweet_count":0,"reply_count":0,"like_count":2,"quote_count":0},"created_at":"2018-03-14T17:07:29.000Z","conversation_id":"973937331991322625","id":"973968874113728512","lang":"en","in_reply_to_user_id":"262884082","referenced_tweets":[{"type":"replied_to","id":"973957234504876032"}],"geo":{},"attachments":{"media_keys":{}},"Player":"FCHWPO","DateTime":"2018-03-14 20:00:00","GameId":"201803140BOS"},{"entities":{"annotations":{},"mentions":[{"start":0,"end":11,"username":"migifatboy"},{"start":28,"end":42,"username":"jerome_randle"},{"start":43,"end":55,"username":"DevInTheLab"},{"start":56,"end":63,"username":"FCHWPO"},{"start":64,"end":74,"username":"YoungIvee"}],"hashtags":{},"urls":{}},"source":"Twitter for iPhone","possibly_sensitive":false,"context_annotations":[{"domain":{"id":"10","name":"Person","description":"Named people in the world like Nelson Mandela"},"entity":{"id":"809849116989632513","name":"Jaylen Brown"}},{"domain":{"id":"10","name":"Person","description":"Named people in the world like Nelson Mandela"},"entity":{"id":"840230724779229187","name":"Ivan Rabb"}},{"domain":{"id":"60","name":"Athlete","description":"An athlete in the world, like Serena Williams or Lionel Messi"},"entity":{"id":"809849116989632513","name":"Jaylen Brown"}},{"domain":{"id":"60","name":"Athlete","description":"An athlete in the world, like Serena Williams or Lionel Messi"},"entity":{"id":"840230724779229187","name":"Ivan Rabb"}}],"author_id":"262884082","text":"@migifatboy @valandrelaguna @jerome_randle @DevInTheLab @FCHWPO @YoungIvee Only for you I want a close up angle too 🤩","public_metrics":{"retweet_count":0,"reply_count":1,"like_count":3,"quote_count":0},"created_at":"2018-03-14T16:21:14.000Z","conversation_id":"973937331991322625","id":"973957234504876032","lang":"en","in_reply_to_user_id":"242536562","referenced_tweets":[{"type":"replied_to","id":"973956151690846209"}],"geo":{},"attachments":{"media_keys":{}},"Player":"FCHWPO","DateTime":"2018-03-14 20:00:00","GameId":"201803140BOS"},{"entities":{"annotations":{},"mentions":[{"start":0,"end":10,"username":"halfaflip"},{"start":27,"end":41,"username":"jerome_randle"},{"start":42,"end":54,"username":"DevInTheLab"},{"start":55,"end":62,"username":"FCHWPO"},{"start":63,"end":73,"username":"YoungIvee"}],"hashtags":{},"urls":{}},"source":"Twitter for iPhone","possibly_sensitive":false,"context_annotations":[{"domain":{"id":"10","name":"Person","description":"Named people in the world like Nelson Mandela"},"entity":{"id":"809849116989632513","name":"Jaylen Brown"}},{"domain":{"id":"10","name":"Person","description":"Named people in the world like Nelson Mandela"},"entity":{"id":"840230724779229187","name":"Ivan Rabb"}},{"domain":{"id":"60","name":"Athlete","description":"An athlete in the world, like Serena Williams or Lionel Messi"},"entity":{"id":"809849116989632513","name":"Jaylen Brown"}},{"domain":{"id":"60","name":"Athlete","description":"An athlete in the world, like Serena Williams or Lionel Messi"},"entity":{"id":"840230724779229187","name":"Ivan Rabb"}}],"author_id":"242536562","text":"@halfaflip @valandrelaguna @jerome_randle @DevInTheLab @FCHWPO @YoungIvee Is being shirtless part of this challenge as well?","public_metrics":{"retweet_count":0,"reply_count":1,"like_count":2,"quote_count":0},"created_at":"2018-03-14T16:16:56.000Z","conversation_id":"973937331991322625","id":"973956151690846209","lang":"en","in_reply_to_user_id":"242536562","referenced_tweets":[{"type":"replied_to","id":"973955810303889409"}],"geo":{},"attachments":{"media_keys":{}},"Player":"FCHWPO","DateTime":"2018-03-14 20:00:00","GameId":"201803140BOS"},{"entities":{"annotations":{},"mentions":[{"start":0,"end":10,"username":"halfaflip"},{"start":27,"end":41,"username":"jerome_randle"},{"start":42,"end":54,"username":"DevInTheLab"},{"start":55,"end":62,"username":"FCHWPO"},{"start":63,"end":73,"username":"YoungIvee"}],"hashtags":{},"urls":{}},"source":"Twitter for iPhone","possibly_sensitive":false,"context_annotations":[{"domain":{"id":"10","name":"Person","description":"Named people in the world like Nelson Mandela"},"entity":{"id":"809849116989632513","name":"Jaylen Brown"}},{"domain":{"id":"10","name":"Person","description":"Named people in the world like Nelson Mandela"},"entity":{"id":"840230724779229187","name":"Ivan Rabb"}},{"domain":{"id":"60","name":"Athlete","description":"An athlete in the world, like Serena Williams or Lionel Messi"},"entity":{"id":"809849116989632513","name":"Jaylen Brown"}},{"domain":{"id":"60","name":"Athlete","description":"An athlete in the world, like Serena Williams or Lionel Messi"},"entity":{"id":"840230724779229187","name":"Ivan Rabb"}}],"author_id":"242536562","text":"@halfaflip @valandrelaguna @jerome_randle @DevInTheLab @FCHWPO @YoungIvee Not familiar with this challenge. But seeing where you’re shooting from. I’d cook you. @valandrelaguna you as well brother","public_metrics":{"retweet_count":0,"reply_count":1,"like_count":1,"quote_count":0},"created_at":"2018-03-14T16:15:35.000Z","conversation_id":"973937331991322625","id":"973955810303889409","lang":"en","in_reply_to_user_id":"262884082","referenced_tweets":[{"type":"replied_to","id":"973937331991322625"}],"geo":{},"attachments":{"media_keys":{}},"Player":"FCHWPO","DateTime":"2018-03-14 20:00:00","GameId":"201803140BOS"},{"entities":{"annotations":[{"start":101,"end":111,"probability":0.4813,"type":"Person","normalized_text":"Tommy Point"},{"start":116,"end":119,"probability":0.9431,"type":"Person","normalized_text":"Owen"}],"mentions":[{"start":0,"end":11,"username":"pauldailey"},{"start":12,"end":19,"username":"tvabby"},{"start":20,"end":28,"username":"celtics"},{"start":29,"end":41,"username":"NBCSCeltics"},{"start":42,"end":54,"username":"KyrieIrving"},{"start":55,"end":65,"username":"smart_MS3"},{"start":66,"end":75,"username":"dtheis10"},{"start":76,"end":90,"username":"gordonhayward"},{"start":91,"end":98,"username":"FCHWPO"}],"hashtags":{},"urls":{}},"source":"Twitter for iPhone","possibly_sensitive":false,"context_annotations":[{"domain":{"id":"3","name":"TV Shows","description":"Television shows from around the world"},"entity":{"id":"10000607734","name":"NBA Basketball","description":"All the latest basketball action from the NBA."}},{"domain":{"id":"3","name":"TV Shows","description":"Television shows from around the world"},"entity":{"id":"10029190505","name":"Live: NBA Basketball","description":"Live coverage from the National Basketball Association, the top basketball league in North America."}},{"domain":{"id":"3","name":"TV Shows","description":"Television shows from around the world"},"entity":{"id":"10029304530","name":"NBA Basketball"}},{"domain":{"id":"10","name":"Person","description":"Named people in the world like Nelson Mandela"},"entity":{"id":"912907093786497024","name":"Daniel Theis"}},{"domain":{"id":"12","name":"Sports Team","description":"A sports team organization, like Arsenal and the Boston Celtics"},"entity":{"id":"706083876595068928","name":"Boston Celtics"}},{"domain":{"id":"26","name":"Sports League","description":""},"entity":{"id":"706083889454813185","name":"NBA"}},{"domain":{"id":"60","name":"Athlete","description":"An athlete in the world, like Serena Williams or Lionel Messi"},"entity":{"id":"912907093786497024","name":"Daniel Theis"}},{"domain":{"id":"10","name":"Person","description":"Named people in the world like Nelson Mandela"},"entity":{"id":"809849108659773440","name":"Marcus Smart"}},{"domain":{"id":"10","name":"Person","description":"Named people in the world like Nelson Mandela"},"entity":{"id":"809849112870809601","name":"Kyrie Irving"}},{"domain":{"id":"10","name":"Person","description":"Named people in the world like Nelson Mandela"},"entity":{"id":"809849115597078530","name":"Gordon Hayward"}},{"domain":{"id":"10","name":"Person","description":"Named people in the world like Nelson Mandela"},"entity":{"id":"809849116989632513","name":"Jaylen Brown"}},{"domain":{"id":"60","name":"Athlete","description":"An athlete in the world, like Serena Williams or Lionel Messi"},"entity":{"id":"809849108659773440","name":"Marcus Smart"}},{"domain":{"id":"60","name":"Athlete","description":"An athlete in the world, like Serena Williams or Lionel Messi"},"entity":{"id":"809849112870809601","name":"Kyrie Irving"}},{"domain":{"id":"60","name":"Athlete","description":"An athlete in the world, like Serena Williams or Lionel Messi"},"entity":{"id":"809849115597078530","name":"Gordon Hayward"}},{"domain":{"id":"60","name":"Athlete","description":"An athlete in the world, like Serena Williams or Lionel Messi"},"entity":{"id":"809849116989632513","name":"Jaylen Brown"}}],"author_id":"18140588","text":"@pauldailey @tvabby @celtics @NBCSCeltics @KyrieIrving @smart_MS3 @dtheis10 @gordonhayward @FCHWPO A Tommy Point to Owen for this!","public_metrics":{"retweet_count":0,"reply_count":0,"like_count":1,"quote_count":0},"created_at":"2018-03-14T16:12:44.000Z","conversation_id":"973755962787065856","id":"973955093803491328","lang":"en","in_reply_to_user_id":"33822756","referenced_tweets":[{"type":"replied_to","id":"973755962787065856"}],"geo":{},"attachments":{"media_keys":{}},"Player":"FCHWPO","DateTime":"2018-03-14 20:00:00","GameId":"201803140BOS"},{"entities":{"annotations":{},"mentions":[{"start":0,"end":10,"username":"halfaflip"},{"start":11,"end":26,"username":"berdengarchers"},{"start":43,"end":57,"username":"jerome_randle"},{"start":58,"end":70,"username":"DevInTheLab"},{"start":71,"end":78,"username":"FCHWPO"},{"start":79,"end":89,"username":"YoungIvee"}],"hashtags":{},"urls":{}},"source":"Twitter for iPhone","possibly_sensitive":false,"context_annotations":[{"domain":{"id":"10","name":"Person","description":"Named people in the world like Nelson Mandela"},"entity":{"id":"809849116989632513","name":"Jaylen Brown"}},{"domain":{"id":"10","name":"Person","description":"Named people in the world like Nelson Mandela"},"entity":{"id":"840230724779229187","name":"Ivan Rabb"}},{"domain":{"id":"60","name":"Athlete","description":"An athlete in the world, like Serena Williams or Lionel Messi"},"entity":{"id":"809849116989632513","name":"Jaylen Brown"}},{"domain":{"id":"60","name":"Athlete","description":"An athlete in the world, like Serena Williams or Lionel Messi"},"entity":{"id":"840230724779229187","name":"Ivan Rabb"}}],"author_id":"711507571199205378","text":"@halfaflip @berdengarchers @valandrelaguna @jerome_randle @DevInTheLab @FCHWPO @YoungIvee wowwwwieee so hot. galing!! 🔥💚","public_metrics":{"retweet_count":0,"reply_count":0,"like_count":1,"quote_count":0},"created_at":"2018-03-14T16:02:11.000Z","conversation_id":"973937331991322625","id":"973952439526174720","lang":"en","in_reply_to_user_id":"262884082","referenced_tweets":[{"type":"replied_to","id":"973937331991322625"}],"geo":{},"attachments":{"media_keys":{}},"Player":"FCHWPO","DateTime":"2018-03-14 20:00:00","GameId":"201803140BOS"},{"entities":{"annotations":{},"mentions":[{"start":0,"end":10,"username":"halfaflip"},{"start":27,"end":41,"username":"jerome_randle"},{"start":42,"end":54,"username":"DevInTheLab"},{"start":55,"end":62,"username":"FCHWPO"},{"start":63,"end":73,"username":"YoungIvee"},{"start":108,"end":118,"username":"halfaflip"}],"hashtags":{},"urls":{}},"source":"Twitter for iPhone","possibly_sensitive":false,"context_annotations":[{"domain":{"id":"10","name":"Person","description":"Named people in the world like Nelson Mandela"},"entity":{"id":"809849116989632513","name":"Jaylen Brown"}},{"domain":{"id":"10","name":"Person","description":"Named people in the world like Nelson Mandela"},"entity":{"id":"840230724779229187","name":"Ivan Rabb"}},{"domain":{"id":"60","name":"Athlete","description":"An athlete in the world, like Serena Williams or Lionel Messi"},"entity":{"id":"809849116989632513","name":"Jaylen Brown"}},{"domain":{"id":"60","name":"Athlete","description":"An athlete in the world, like Serena Williams or Lionel Messi"},"entity":{"id":"840230724779229187","name":"Ivan Rabb"}}],"author_id":"1142405670","text":"@halfaflip @valandrelaguna @jerome_randle @DevInTheLab @FCHWPO @YoungIvee Can't wait to see you next season @halfaflip 😍😍","public_metrics":{"retweet_count":0,"reply_count":0,"like_count":0,"quote_count":0},"created_at":"2018-03-14T15:16:48.000Z","conversation_id":"973937331991322625","id":"973941018239188993","lang":"en","in_reply_to_user_id":"262884082","referenced_tweets":[{"type":"replied_to","id":"973937331991322625"}],"geo":{},"attachments":{"media_keys":{}},"Player":"FCHWPO","DateTime":"2018-03-14 20:00:00","GameId":"201803140BOS"},{"entities":{"annotations":{},"mentions":[{"start":0,"end":10,"username":"halfaflip"},{"start":27,"end":41,"username":"jerome_randle"},{"start":42,"end":54,"username":"DevInTheLab"},{"start":55,"end":62,"username":"FCHWPO"},{"start":63,"end":73,"username":"YoungIvee"}],"hashtags":{},"urls":{}},"source":"Twitter for iPhone","possibly_sensitive":false,"context_annotations":[{"domain":{"id":"10","name":"Person","description":"Named people in the world like Nelson Mandela"},"entity":{"id":"809849116989632513","name":"Jaylen Brown"}},{"domain":{"id":"10","name":"Person","description":"Named people in the world like Nelson Mandela"},"entity":{"id":"840230724779229187","name":"Ivan Rabb"}},{"domain":{"id":"60","name":"Athlete","description":"An athlete in the world, like Serena Williams or Lionel Messi"},"entity":{"id":"809849116989632513","name":"Jaylen Brown"}},{"domain":{"id":"60","name":"Athlete","description":"An athlete in the world, like Serena Williams or Lionel Messi"},"entity":{"id":"840230724779229187","name":"Ivan Rabb"}}],"author_id":"231408117","text":"@halfaflip @valandrelaguna @jerome_randle @DevInTheLab @FCHWPO @YoungIvee Put on a shirt","public_metrics":{"retweet_count":1,"reply_count":0,"like_count":5,"quote_count":0},"created_at":"2018-03-14T15:06:43.000Z","conversation_id":"973937331991322625","id":"973938482056867840","lang":"en","in_reply_to_user_id":"262884082","referenced_tweets":[{"type":"replied_to","id":"973937331991322625"}],"geo":{"place_id":"011a05612b6a331c"},"attachments":{"media_keys":{}},"Player":"FCHWPO","DateTime":"2018-03-14 20:00:00","GameId":"201803140BOS"},{"entities":{"annotations":{},"mentions":[{"start":35,"end":43,"username":"celtics"},{"start":102,"end":109,"username":"FCHWPO"}],"hashtags":{},"urls":[{"start":113,"end":136,"url":"https://t.co/TBk2rPxrKc","expanded_url":"https://jersey-jeans.myshopify.com/products/downtown-brown","display_url":"jersey-jeans.myshopify.com/products/downt…"},{"start":137,"end":160,"url":"https://t.co/J3gP1kdbSR","expanded_url":"https://twitter.com/JerseyJeans23/status/973937623675781121/photo/1","display_url":"pic.twitter.com/J3gP1kdbSR"},{"start":137,"end":160,"url":"https://t.co/J3gP1kdbSR","expanded_url":"https://twitter.com/JerseyJeans23/status/973937623675781121/photo/1","display_url":"pic.twitter.com/J3gP1kdbSR"}]},"source":"Twitter for iPhone","possibly_sensitive":false,"context_annotations":[{"domain":{"id":"3","name":"TV Shows","description":"Television shows from around the world"},"entity":{"id":"10000607734","name":"NBA Basketball","description":"All the latest basketball action from the NBA."}},{"domain":{"id":"3","name":"TV Shows","description":"Television shows from around the world"},"entity":{"id":"10029190505","name":"Live: NBA Basketball","description":"Live coverage from the National Basketball Association, the top basketball league in North America."}},{"domain":{"id":"3","name":"TV Shows","description":"Television shows from around the world"},"entity":{"id":"10029304530","name":"NBA Basketball"}},{"domain":{"id":"12","name":"Sports Team","description":"A sports team organization, like Arsenal and the Boston Celtics"},"entity":{"id":"706083876595068928","name":"Boston Celtics"}},{"domain":{"id":"26","name":"Sports League","description":""},"entity":{"id":"706083889454813185","name":"NBA"}},{"domain":{"id":"10","name":"Person","description":"Named people in the world like Nelson Mandela"},"entity":{"id":"809849116989632513","name":"Jaylen Brown"}},{"domain":{"id":"60","name":"Athlete","description":"An athlete in the world, like Serena Williams or Lionel Messi"},"entity":{"id":"809849116989632513","name":"Jaylen Brown"}}],"author_id":"841869771666792448","text":"Shoutout to @classic006_mmc at the @celtics game rocking his “Downtown Brown” Jersey Jacket featuring @FCHWPO. \n\nhttps://t.co/TBk2rPxrKc https://t.co/J3gP1kdbSR","public_metrics":{"retweet_count":0,"reply_count":0,"like_count":1,"quote_count":0},"created_at":"2018-03-14T15:03:19.000Z","conversation_id":"973937623675781121","id":"973937623675781121","lang":"en","referenced_tweets":{},"geo":{},"attachments":{"media_keys":["3_973937601580171264","3_973937601580171266"]},"Player":"FCHWPO","DateTime":"2018-03-14 20:00:00","GameId":"201803140BOS"},{"entities":{"annotations":{},"mentions":[{"start":155,"end":169,"username":"jerome_randle"},{"start":170,"end":182,"username":"DevInTheLab"},{"start":184,"end":191,"username":"FCHWPO"},{"start":193,"end":203,"username":"YoungIvee"}],"hashtags":[{"start":8,"end":26,"tag":"quickgunchallenge"}],"urls":[{"start":204,"end":227,"url":"https://t.co/XBgH2YRz8t","expanded_url":"https://twitter.com/halfaflip/status/973937331991322625/video/1","display_url":"pic.twitter.com/XBgH2YRz8t"}]},"source":"Twitter for iPhone","possibly_sensitive":false,"context_annotations":[{"domain":{"id":"10","name":"Person","description":"Named people in the world like Nelson Mandela"},"entity":{"id":"809849116989632513","name":"Jaylen Brown"}},{"domain":{"id":"10","name":"Person","description":"Named people in the world like Nelson Mandela"},"entity":{"id":"840230724779229187","name":"Ivan Rabb"}},{"domain":{"id":"60","name":"Athlete","description":"An athlete in the world, like Serena Williams or Lionel Messi"},"entity":{"id":"809849116989632513","name":"Jaylen Brown"}},{"domain":{"id":"60","name":"Athlete","description":"An athlete in the world, like Serena Williams or Lionel Messi"},"entity":{"id":"840230724779229187","name":"Ivan Rabb"}}],"author_id":"262884082","text":"Hit the #quickgunchallenge after workouts today. \n\nHope B gives me a couple bouns points for the extra 1.35 feet \n\nI’ll try again soon 👌🏼🎯@valandrelaguna \n@jerome_randle\n@DevInTheLab \n@FCHWPO \n@YoungIvee https://t.co/XBgH2YRz8t","public_metrics":{"retweet_count":81,"reply_count":18,"like_count":574,"quote_count":44},"created_at":"2018-03-14T15:02:09.000Z","conversation_id":"973937331991322625","id":"973937331991322625","lang":"en","referenced_tweets":{},"geo":{},"attachments":{"media_keys":["7_973936454920318976"]},"Player":"FCHWPO","DateTime":"2018-03-14 20:00:00","GameId":"201803140BOS"},{"entities":{"annotations":{},"mentions":[{"start":0,"end":10,"username":"ByJayKing"},{"start":11,"end":18,"username":"FCHWPO"}],"hashtags":{},"urls":{}},"source":"Twitter for iPhone","possibly_sensitive":false,"context_annotations":[{"domain":{"id":"10","name":"Person","description":"Named people in the world like Nelson Mandela"},"entity":{"id":"809849116989632513","name":"Jaylen Brown"}},{"domain":{"id":"60","name":"Athlete","description":"An athlete in the world, like Serena Williams or Lionel Messi"},"entity":{"id":"809849116989632513","name":"Jaylen Brown"}}],"author_id":"891936318","text":"@ByJayKing @FCHWPO has the same problem","public_metrics":{"retweet_count":0,"reply_count":0,"like_count":0,"quote_count":0},"created_at":"2018-03-14T14:41:05.000Z","conversation_id":"973864833463521280","id":"973932032354148353","lang":"en","in_reply_to_user_id":"38032945","referenced_tweets":[{"type":"replied_to","id":"973864833463521280"}],"geo":{},"attachments":{"media_keys":{}},"Player":"FCHWPO","DateTime":"2018-03-14 20:00:00","GameId":"201803140BOS"},{"entities":{"annotations":{},"mentions":[{"start":7,"end":15,"username":"celtics"},{"start":30,"end":42,"username":"KyrieIrving"},{"start":58,"end":65,"username":"FCHWPO"},{"start":76,"end":87,"username":"Al_Horford"},{"start":92,"end":104,"username":"WashWizards"}],"hashtags":[{"start":44,"end":56,"tag":"MarcusSmart"}],"urls":[{"start":106,"end":129,"url":"https://t.co/i9wqmUqjup","expanded_url":"https://www.thescore.com/nba/news/1504349","display_url":"thescore.com/nba/news/15043…"}]},"source":"Twitter for iPhone","possibly_sensitive":false,"context_annotations":[{"domain":{"id":"3","name":"TV Shows","description":"Television shows from around the world"},"entity":{"id":"10000607734","name":"NBA Basketball","description":"All the latest basketball action from the NBA."}},{"domain":{"id":"3","name":"TV Shows","description":"Television shows from around the world"},"entity":{"id":"10029190505","name":"Live: NBA Basketball","description":"Live coverage from the National Basketball Association, the top basketball league in North America."}},{"domain":{"id":"3","name":"TV Shows","description":"Television shows from around the world"},"entity":{"id":"10029304530","name":"NBA Basketball"}},{"domain":{"id":"10","name":"Person","description":"Named people in the world like Nelson Mandela"},"entity":{"id":"809849107590180865","name":"Al Horford"}},{"domain":{"id":"12","name":"Sports Team","description":"A sports team organization, like Arsenal and the Boston Celtics"},"entity":{"id":"706083847893442560","name":"Washington Wizards"}},{"domain":{"id":"12","name":"Sports Team","description":"A sports team organization, like Arsenal and the Boston Celtics"},"entity":{"id":"706083876595068928","name":"Boston Celtics"}},{"domain":{"id":"26","name":"Sports League","description":""},"entity":{"id":"706083889454813185","name":"NBA"}},{"domain":{"id":"60","name":"Athlete","description":"An athlete in the world, like Serena Williams or Lionel Messi"},"entity":{"id":"809849107590180865","name":"Al Horford"}},{"domain":{"id":"10","name":"Person","description":"Named people in the world like Nelson Mandela"},"entity":{"id":"809849108659773440","name":"Marcus Smart"}},{"domain":{"id":"10","name":"Person","description":"Named people in the world like Nelson Mandela"},"entity":{"id":"809849112870809601","name":"Kyrie Irving"}},{"domain":{"id":"10","name":"Person","description":"Named people in the world like Nelson Mandela"},"entity":{"id":"809849116989632513","name":"Jaylen Brown"}},{"domain":{"id":"60","name":"Athlete","description":"An athlete in the world, like Serena Williams or Lionel Messi"},"entity":{"id":"809849108659773440","name":"Marcus Smart"}},{"domain":{"id":"60","name":"Athlete","description":"An athlete in the world, like Serena Williams or Lionel Messi"},"entity":{"id":"809849112870809601","name":"Kyrie Irving"}},{"domain":{"id":"60","name":"Athlete","description":"An athlete in the world, like Serena Williams or Lionel Messi"},"entity":{"id":"809849116989632513","name":"Jaylen Brown"}}],"author_id":"118811691","text":"Wow! - @celtics to be without @KyrieIrving, #MarcusSmart, @FCHWPO, possibly @Al_Horford vs. @WashWizards  https://t.co/i9wqmUqjup","public_metrics":{"retweet_count":0,"reply_count":0,"like_count":0,"quote_count":0},"created_at":"2018-03-14T13:46:30.000Z","conversation_id":"973918292657278976","id":"973918292657278976","lang":"en","referenced_tweets":{},"geo":{},"attachments":{"media_keys":{}},"Player":"FCHWPO","DateTime":"2018-03-14 20:00:00","GameId":"201803140BOS"},{"entities":{"annotations":[{"start":119,"end":123,"probability":0.8163,"type":"Person","normalized_text":"JESUS"},{"start":249,"end":251,"probability":0.691,"type":"Other","normalized_text":"GOD"},{"start":265,"end":267,"probability":0.5709,"type":"Other","normalized_text":"GOD"}],"mentions":[{"start":26,"end":33,"username":"FCHWPO"}],"hashtags":[{"start":282,"end":288,"tag":"ARISE"}],"urls":{}},"source":"Twitter Web App","possibly_sensitive":false,"context_annotations":[{"domain":{"id":"10","name":"Person","description":"Named people in the world like Nelson Mandela"},"entity":{"id":"809849116989632513","name":"Jaylen Brown"}},{"domain":{"id":"60","name":"Athlete","description":"An athlete in the world, like Serena Williams or Lionel Messi"},"entity":{"id":"809849116989632513","name":"Jaylen Brown"}}],"author_id":"753187516887527424","text":"OK LETS GO IN FOR JAYLEN! @FCHWPO\nBELOVED, FAITH, CONSISTENCY &amp; HARD WORK PAYS OFF!\nIT WILL BE SO FOR U IN THE NAME OF JESUS!\nWE LOVE U J BROWN &amp; LOOK FOR THE AUTHORITIES TO INVESTIGATE WHATS HAPPENING TO U NOW!\nDIVINE INTERVENTION IS OUR PRAYER TO GOD!\nWE BELIEVE GOD 4 U! #ARISE","public_metrics":{"retweet_count":0,"reply_count":1,"like_count":0,"quote_count":0},"created_at":"2018-03-14T11:58:23.000Z","conversation_id":"973882996112621568","id":"973891087453614081","lang":"en","in_reply_to_user_id":"753187516887527424","referenced_tweets":[{"type":"replied_to","id":"973885891428126720"}],"geo":{},"attachments":{"media_keys":{}},"Player":"FCHWPO","DateTime":"2018-03-14 20:00:00","GameId":"201803140BOS"},{"entities":{"annotations":{},"mentions":[{"start":16,"end":28,"username":"DevInTheLab"},{"start":29,"end":33,"username":"GWR"},{"start":34,"end":41,"username":"FCHWPO"},{"start":42,"end":52,"username":"YoungIvee"}],"hashtags":{},"urls":{}},"source":"Twitter for iPhone","possibly_sensitive":false,"context_annotations":[{"domain":{"id":"10","name":"Person","description":"Named people in the world like Nelson Mandela"},"entity":{"id":"809849116989632513","name":"Jaylen Brown"}},{"domain":{"id":"10","name":"Person","description":"Named people in the world like Nelson Mandela"},"entity":{"id":"840230724779229187","name":"Ivan Rabb"}},{"domain":{"id":"60","name":"Athlete","description":"An athlete in the world, like Serena Williams or Lionel Messi"},"entity":{"id":"809849116989632513","name":"Jaylen Brown"}},{"domain":{"id":"60","name":"Athlete","description":"An athlete in the world, like Serena Williams or Lionel Messi"},"entity":{"id":"840230724779229187","name":"Ivan Rabb"}}],"author_id":"565074825","text":"@valandrelaguna @DevInTheLab @GWR @FCHWPO @YoungIvee okay thanx 4 giving me some time 2 work on my Shit I’ll see what I can put together lol","public_metrics":{"retweet_count":0,"reply_count":1,"like_count":2,"quote_count":0},"created_at":"2018-03-14T07:25:43.000Z","conversation_id":"973713949572018181","id":"973822465444020226","lang":"en","in_reply_to_user_id":"442098386","referenced_tweets":[{"type":"replied_to","id":"973812846172794882"}],"geo":{"place_id":"b9b77321807927e1"},"attachments":{"media_keys":{}},"Player":"FCHWPO","DateTime":"2018-03-14 20:00:00","GameId":"201803140BOS"},{"entities":{"annotations":[{"start":76,"end":91,"probability":0.3433,"type":"Other","normalized_text":"The Untouchables"}],"mentions":[{"start":0,"end":11,"username":"SteveBHoop"},{"start":12,"end":19,"username":"FCHWPO"}],"hashtags":{},"urls":{}},"source":"Twitter Web App","possibly_sensitive":false,"context_annotations":[{"domain":{"id":"10","name":"Person","description":"Named people in the world like Nelson Mandela"},"entity":{"id":"809849116989632513","name":"Jaylen Brown"}},{"domain":{"id":"11","name":"Sport","description":"Types of sports, like soccer and basketball"},"entity":{"id":"706083902411055104","name":"Basketball"}},{"domain":{"id":"60","name":"Athlete","description":"An athlete in the world, like Serena Williams or Lionel Messi"},"entity":{"id":"809849116989632513","name":"Jaylen Brown"}}],"author_id":"449322871","text":"@SteveBHoop @FCHWPO Love that movie, but it's as much a basketball movie as The Untouchables is about tax evasion.","public_metrics":{"retweet_count":0,"reply_count":0,"like_count":0,"quote_count":0},"created_at":"2018-03-14T06:59:32.000Z","conversation_id":"973738184847839236","id":"973815879350747138","lang":"en","in_reply_to_user_id":"516599568","referenced_tweets":[{"type":"replied_to","id":"973738184847839236"}],"geo":{},"attachments":{"media_keys":{}},"Player":"FCHWPO","DateTime":"2018-03-14 20:00:00","GameId":"201803140BOS"},{"entities":{"annotations":{},"mentions":[{"start":0,"end":7,"username":"FCHWPO"}],"hashtags":{},"urls":{}},"source":"Twitter for iPhone","possibly_sensitive":false,"context_annotations":[{"domain":{"id":"10","name":"Person","description":"Named people in the world like Nelson Mandela"},"entity":{"id":"809849116989632513","name":"Jaylen Brown"}},{"domain":{"id":"60","name":"Athlete","description":"An athlete in the world, like Serena Williams or Lionel Messi"},"entity":{"id":"809849116989632513","name":"Jaylen Brown"}}],"author_id":"88526686","text":"@FCHWPO is bae‼️","public_metrics":{"retweet_count":0,"reply_count":0,"like_count":0,"quote_count":0},"created_at":"2018-03-14T06:57:43.000Z","conversation_id":"973815418904334336","id":"973815418904334336","lang":"tl","in_reply_to_user_id":"419181069","referenced_tweets":{},"geo":{},"attachments":{"media_keys":{}},"Player":"FCHWPO","DateTime":"2018-03-14 20:00:00","GameId":"201803140BOS"},{"entities":{"annotations":{},"mentions":{},"hashtags":{},"urls":[{"start":12,"end":35,"url":"https://t.co/UMADE7WmRN","expanded_url":"https://twitter.com/fchwpo/status/971978189877608454","display_url":"twitter.com/fchwpo/status/…"}]},"source":"Twitter for iPhone","possibly_sensitive":false,"context_annotations":{},"author_id":"2921218050","text":"I miss you. https://t.co/UMADE7WmRN","public_metrics":{"retweet_count":0,"reply_count":0,"like_count":0,"quote_count":0},"created_at":"2018-03-14T05:47:02.000Z","conversation_id":"973797632203255809","id":"973797632203255809","lang":"en","referenced_tweets":[{"type":"quoted","id":"971978189877608454"}],"geo":{"place_id":"c6dc3c4bfa85ba10"},"attachments":{"media_keys":{}},"Player":"FCHWPO","DateTime":"2018-03-14 20:00:00","GameId":"201803140BOS"},{"entities":{"annotations":[{"start":19,"end":25,"probability":0.571,"type":"Organization","normalized_text":"Celtics"}],"mentions":[{"start":77,"end":89,"username":"KyrieIrving"},{"start":94,"end":104,"username":"smart_MS3"},{"start":109,"end":116,"username":"FCHWPO"},{"start":121,"end":130,"username":"dtheis10"},{"start":135,"end":149,"username":"gordonhayward"}],"hashtags":{},"urls":{}},"source":"Twitter for iPhone","possibly_sensitive":false,"context_annotations":[{"domain":{"id":"3","name":"TV Shows","description":"Television shows from around the world"},"entity":{"id":"10000607734","name":"NBA Basketball","description":"All the latest basketball action from the NBA."}},{"domain":{"id":"10","name":"Person","description":"Named people in the world like Nelson Mandela"},"entity":{"id":"912907093786497024","name":"Daniel Theis"}},{"domain":{"id":"12","name":"Sports Team","description":"A sports team organization, like Arsenal and the Boston Celtics"},"entity":{"id":"706083876595068928","name":"Boston Celtics"}},{"domain":{"id":"26","name":"Sports League","description":""},"entity":{"id":"706083889454813185","name":"NBA"}},{"domain":{"id":"60","name":"Athlete","description":"An athlete in the world, like Serena Williams or Lionel Messi"},"entity":{"id":"912907093786497024","name":"Daniel Theis"}},{"domain":{"id":"10","name":"Person","description":"Named people in the world like Nelson Mandela"},"entity":{"id":"809849108659773440","name":"Marcus Smart"}},{"domain":{"id":"10","name":"Person","description":"Named people in the world like Nelson Mandela"},"entity":{"id":"809849112870809601","name":"Kyrie Irving"}},{"domain":{"id":"10","name":"Person","description":"Named people in the world like Nelson Mandela"},"entity":{"id":"809849115597078530","name":"Gordon Hayward"}},{"domain":{"id":"10","name":"Person","description":"Named people in the world like Nelson Mandela"},"entity":{"id":"809849116989632513","name":"Jaylen Brown"}},{"domain":{"id":"60","name":"Athlete","description":"An athlete in the world, like Serena Williams or Lionel Messi"},"entity":{"id":"809849108659773440","name":"Marcus Smart"}},{"domain":{"id":"60","name":"Athlete","description":"An athlete in the world, like Serena Williams or Lionel Messi"},"entity":{"id":"809849112870809601","name":"Kyrie Irving"}},{"domain":{"id":"60","name":"Athlete","description":"An athlete in the world, like Serena Williams or Lionel Messi"},"entity":{"id":"809849115597078530","name":"Gordon Hayward"}},{"domain":{"id":"60","name":"Athlete","description":"An athlete in the world, like Serena Williams or Lionel Messi"},"entity":{"id":"809849116989632513","name":"Jaylen Brown"}}],"author_id":"379277680","text":"Going to the Magic/Celtics game Friday &amp; half the team hurt. Probably NO @KyrieIrving, NO @smart_MS3, NO @FCHWPO, NO @dtheis10, NO @gordonhayward 😫😫😫 I need an autographed picture or something.","public_metrics":{"retweet_count":0,"reply_count":1,"like_count":0,"quote_count":0},"created_at":"2018-03-14T04:11:33.000Z","conversation_id":"973773604423913473","id":"973773604423913473","lang":"en","referenced_tweets":{},"geo":{},"attachments":{"media_keys":{}},"Player":"FCHWPO","DateTime":"2018-03-14 20:00:00","GameId":"201803140BOS"},{"entities":{"annotations":{},"mentions":[{"start":0,"end":12,"username":"celticsblog"},{"start":13,"end":24,"username":"SteveBHoop"},{"start":25,"end":32,"username":"FCHWPO"}],"hashtags":{},"urls":{}},"source":"Twitter for iPhone","possibly_sensitive":false,"context_annotations":[{"domain":{"id":"10","name":"Person","description":"Named people in the world like Nelson Mandela"},"entity":{"id":"809849116989632513","name":"Jaylen Brown"}},{"domain":{"id":"11","name":"Sport","description":"Types of sports, like soccer and basketball"},"entity":{"id":"706083902411055104","name":"Basketball"}},{"domain":{"id":"60","name":"Athlete","description":"An athlete in the world, like Serena Williams or Lionel Messi"},"entity":{"id":"809849116989632513","name":"Jaylen Brown"}}],"author_id":"16353106","text":"@celticsblog @SteveBHoop @FCHWPO You said that my skills reached ‘farther’ than basketball. ‘Farther’ relaates to distance, ‘further’ is a definition of degree. You should have said ‘further’.","public_metrics":{"retweet_count":0,"reply_count":0,"like_count":1,"quote_count":0},"created_at":"2018-03-14T03:13:54.000Z","conversation_id":"973738184847839236","id":"973759094195548160","lang":"en","in_reply_to_user_id":"14331674","referenced_tweets":[{"type":"replied_to","id":"973739373790449664"}],"geo":{},"attachments":{"media_keys":{}},"Player":"FCHWPO","DateTime":"2018-03-14 20:00:00","GameId":"201803140BOS"},{"entities":{"annotations":[{"start":53,"end":59,"probability":0.8245,"type":"Organization","normalized_text":"Celtics"},{"start":123,"end":129,"probability":0.6356,"type":"Organization","normalized_text":"Celtics"}],"mentions":[{"start":5,"end":12,"username":"FCHWPO"},{"start":13,"end":23,"username":"smart_MS3"},{"start":30,"end":42,"username":"KyrieIrving"},{"start":97,"end":111,"username":"gordonhayward"}],"hashtags":{},"urls":{}},"source":"Twitter for Android","possibly_sensitive":false,"context_annotations":[{"domain":{"id":"3","name":"TV Shows","description":"Television shows from around the world"},"entity":{"id":"10000607734","name":"NBA Basketball","description":"All the latest basketball action from the NBA."}},{"domain":{"id":"12","name":"Sports Team","description":"A sports team organization, like Arsenal and the Boston Celtics"},"entity":{"id":"706083876595068928","name":"Boston Celtics"}},{"domain":{"id":"26","name":"Sports League","description":""},"entity":{"id":"706083889454813185","name":"NBA"}},{"domain":{"id":"10","name":"Person","description":"Named people in the world like Nelson Mandela"},"entity":{"id":"809849108659773440","name":"Marcus Smart"}},{"domain":{"id":"10","name":"Person","description":"Named people in the world like Nelson Mandela"},"entity":{"id":"809849112870809601","name":"Kyrie Irving"}},{"domain":{"id":"10","name":"Person","description":"Named people in the world like Nelson Mandela"},"entity":{"id":"809849115597078530","name":"Gordon Hayward"}},{"domain":{"id":"10","name":"Person","description":"Named people in the world like Nelson Mandela"},"entity":{"id":"809849116989632513","name":"Jaylen Brown"}},{"domain":{"id":"60","name":"Athlete","description":"An athlete in the world, like Serena Williams or Lionel Messi"},"entity":{"id":"809849108659773440","name":"Marcus Smart"}},{"domain":{"id":"60","name":"Athlete","description":"An athlete in the world, like Serena Williams or Lionel Messi"},"entity":{"id":"809849112870809601","name":"Kyrie Irving"}},{"domain":{"id":"60","name":"Athlete","description":"An athlete in the world, like Serena Williams or Lionel Messi"},"entity":{"id":"809849115597078530","name":"Gordon Hayward"}},{"domain":{"id":"60","name":"Athlete","description":"An athlete in the world, like Serena Williams or Lionel Messi"},"entity":{"id":"809849116989632513","name":"Jaylen Brown"}}],"author_id":"970776293515120641","text":"When @FCHWPO @smart_MS3 &amp; @KyrieIrving come back.... Celtics will be a force again. Now when @gordonhayward comes back.... Celtics will be unstoppable.","public_metrics":{"retweet_count":0,"reply_count":0,"like_count":0,"quote_count":0},"created_at":"2018-03-14T02:18:34.000Z","conversation_id":"973745169710370816","id":"973745169710370816","lang":"en","referenced_tweets":{},"geo":{},"attachments":{"media_keys":{}},"Player":"FCHWPO","DateTime":"2018-03-14 20:00:00","GameId":"201803140BOS"},{"entities":{"annotations":[{"start":52,"end":63,"probability":0.9331,"type":"Person","normalized_text":"Jaylen Brown"}],"mentions":[{"start":167,"end":174,"username":"FCHWPO"}],"hashtags":{},"urls":[{"start":179,"end":202,"url":"https://t.co/PWf67kehQc","expanded_url":"https://twitter.com/SamilArtt/status/973743719311728640/photo/1","display_url":"pic.twitter.com/PWf67kehQc"}]},"source":"Twitter for iPhone","possibly_sensitive":false,"context_annotations":[{"domain":{"id":"10","name":"Person","description":"Named people in the world like Nelson Mandela"},"entity":{"id":"809849116989632513","name":"Jaylen Brown"}},{"domain":{"id":"60","name":"Athlete","description":"An athlete in the world, like Serena Williams or Lionel Messi"},"entity":{"id":"809849116989632513","name":"Jaylen Brown"}}],"author_id":"1869363511","text":"It’s been a year since I created this painting. The Jaylen Brown painting has transformed me and gave me the confidence to achieve anything that gets in my way today. @FCHWPO 🏀☘️ https://t.co/PWf67kehQc","public_metrics":{"retweet_count":2,"reply_count":0,"like_count":11,"quote_count":0},"created_at":"2018-03-14T02:12:48.000Z","conversation_id":"973743719311728640","id":"973743719311728640","lang":"en","referenced_tweets":{},"geo":{"place_id":"cd450c94084cbf9b"},"attachments":{"media_keys":["3_973743708377092097"]},"Player":"FCHWPO","DateTime":"2018-03-14 20:00:00","GameId":"201803140BOS"},{"entities":{"annotations":{},"mentions":[{"start":0,"end":11,"username":"SteveBHoop"},{"start":12,"end":19,"username":"FCHWPO"}],"hashtags":{},"urls":{}},"source":"Twitter for iPhone","possibly_sensitive":false,"context_annotations":[{"domain":{"id":"10","name":"Person","description":"Named people in the world like Nelson Mandela"},"entity":{"id":"809849116989632513","name":"Jaylen Brown"}},{"domain":{"id":"60","name":"Athlete","description":"An athlete in the world, like Serena Williams or Lionel Messi"},"entity":{"id":"809849116989632513","name":"Jaylen Brown"}}],"author_id":"383286715","text":"@SteveBHoop @FCHWPO I feel old.","public_metrics":{"retweet_count":0,"reply_count":0,"like_count":0,"quote_count":0},"created_at":"2018-03-14T01:57:49.000Z","conversation_id":"973738184847839236","id":"973739947046957056","lang":"en","in_reply_to_user_id":"516599568","referenced_tweets":[{"type":"replied_to","id":"973738184847839236"}],"geo":{},"attachments":{"media_keys":{}},"Player":"FCHWPO","DateTime":"2018-03-14 20:00:00","GameId":"201803140BOS"},{"entities":{"annotations":{},"mentions":[{"start":0,"end":11,"username":"SteveBHoop"},{"start":12,"end":19,"username":"FCHWPO"}],"hashtags":{},"urls":{}},"source":"Twitter for iPhone","possibly_sensitive":false,"context_annotations":[{"domain":{"id":"10","name":"Person","description":"Named people in the world like Nelson Mandela"},"entity":{"id":"809849116989632513","name":"Jaylen Brown"}},{"domain":{"id":"60","name":"Athlete","description":"An athlete in the world, like Serena Williams or Lionel Messi"},"entity":{"id":"809849116989632513","name":"Jaylen Brown"}}],"author_id":"383286715","text":"@SteveBHoop @FCHWPO I love that.","public_metrics":{"retweet_count":0,"reply_count":0,"like_count":0,"quote_count":0},"created_at":"2018-03-14T01:57:34.000Z","conversation_id":"973738184847839236","id":"973739885210292225","lang":"en","in_reply_to_user_id":"516599568","referenced_tweets":[{"type":"replied_to","id":"973738184847839236"}],"geo":{},"attachments":{"media_keys":{}},"Player":"FCHWPO","DateTime":"2018-03-14 20:00:00","GameId":"201803140BOS"},{"entities":{"annotations":{},"mentions":[{"start":0,"end":12,"username":"celticsblog"},{"start":13,"end":24,"username":"SteveBHoop"},{"start":25,"end":32,"username":"FCHWPO"}],"hashtags":{},"urls":{}},"source":"Twitter Web Client","possibly_sensitive":false,"context_annotations":[{"domain":{"id":"10","name":"Person","description":"Named people in the world like Nelson Mandela"},"entity":{"id":"809849116989632513","name":"Jaylen Brown"}},{"domain":{"id":"60","name":"Athlete","description":"An athlete in the world, like Serena Williams or Lionel Messi"},"entity":{"id":"809849116989632513","name":"Jaylen Brown"}}],"author_id":"371076519","text":"@celticsblog @SteveBHoop @FCHWPO you're the man now, dog!","public_metrics":{"retweet_count":0,"reply_count":0,"like_count":1,"quote_count":0},"created_at":"2018-03-14T01:56:28.000Z","conversation_id":"973738184847839236","id":"973739608864370688","lang":"en","in_reply_to_user_id":"14331674","referenced_tweets":[{"type":"replied_to","id":"973739373790449664"}],"geo":{},"attachments":{"media_keys":{}},"Player":"FCHWPO","DateTime":"2018-03-14 20:00:00","GameId":"201803140BOS"},{"entities":{"annotations":{},"mentions":[{"start":0,"end":11,"username":"SteveBHoop"},{"start":12,"end":19,"username":"FCHWPO"}],"hashtags":{},"urls":{}},"source":"Twitter for iPhone","possibly_sensitive":false,"context_annotations":[{"domain":{"id":"10","name":"Person","description":"Named people in the world like Nelson Mandela"},"entity":{"id":"809849116989632513","name":"Jaylen Brown"}},{"domain":{"id":"60","name":"Athlete","description":"An athlete in the world, like Serena Williams or Lionel Messi"},"entity":{"id":"809849116989632513","name":"Jaylen Brown"}}],"author_id":"14331674","text":"@SteveBHoop @FCHWPO 100% agree","public_metrics":{"retweet_count":0,"reply_count":2,"like_count":5,"quote_count":0},"created_at":"2018-03-14T01:55:32.000Z","conversation_id":"973738184847839236","id":"973739373790449664","lang":"en","in_reply_to_user_id":"516599568","referenced_tweets":[{"type":"replied_to","id":"973738184847839236"}],"geo":{},"attachments":{"media_keys":{}},"Player":"FCHWPO","DateTime":"2018-03-14 20:00:00","GameId":"201803140BOS"},{"entities":{"annotations":[{"start":72,"end":88,"probability":0.2824,"type":"Person","normalized_text":"Finding Forrester"}],"mentions":[{"start":5,"end":12,"username":"FCHWPO"}],"hashtags":{},"urls":{}},"source":"Twitter for Android","possibly_sensitive":false,"context_annotations":[{"domain":{"id":"10","name":"Person","description":"Named people in the world like Nelson Mandela"},"entity":{"id":"809849116989632513","name":"Jaylen Brown"}},{"domain":{"id":"11","name":"Sport","description":"Types of sports, like soccer and basketball"},"entity":{"id":"706083902411055104","name":"Basketball"}},{"domain":{"id":"60","name":"Athlete","description":"An athlete in the world, like Serena Williams or Lionel Messi"},"entity":{"id":"809849116989632513","name":"Jaylen Brown"}}],"author_id":"516599568","text":"Hope @FCHWPO can use some of his prescribed recovery time to check out \"Finding Forrester.\" Guaranteed him it would make his list of top basketball movies.","public_metrics":{"retweet_count":2,"reply_count":4,"like_count":21,"quote_count":0},"created_at":"2018-03-14T01:50:49.000Z","conversation_id":"973738184847839236","id":"973738184847839236","lang":"en","referenced_tweets":{},"geo":{},"attachments":{"media_keys":{}},"Player":"FCHWPO","DateTime":"2018-03-14 20:00:00","GameId":"201803140BOS"},{"entities":{"annotations":{},"mentions":[{"start":16,"end":20,"username":"GWR"},{"start":21,"end":35,"username":"jerome_randle"},{"start":36,"end":43,"username":"FCHWPO"},{"start":44,"end":54,"username":"YoungIvee"}],"hashtags":{},"urls":{}},"source":"Twitter for iPhone","possibly_sensitive":false,"context_annotations":[{"domain":{"id":"10","name":"Person","description":"Named people in the world like Nelson Mandela"},"entity":{"id":"809849116989632513","name":"Jaylen Brown"}},{"domain":{"id":"10","name":"Person","description":"Named people in the world like Nelson Mandela"},"entity":{"id":"840230724779229187","name":"Ivan Rabb"}},{"domain":{"id":"60","name":"Athlete","description":"An athlete in the world, like Serena Williams or Lionel Messi"},"entity":{"id":"809849116989632513","name":"Jaylen Brown"}},{"domain":{"id":"60","name":"Athlete","description":"An athlete in the world, like Serena Williams or Lionel Messi"},"entity":{"id":"840230724779229187","name":"Ivan Rabb"}}],"author_id":"159684238","text":"@valandrelaguna @GWR @jerome_randle @FCHWPO @YoungIvee You probably filmed for 3 hours just to get this one minute","public_metrics":{"retweet_count":0,"reply_count":1,"like_count":14,"quote_count":0},"created_at":"2018-03-14T00:22:25.000Z","conversation_id":"973713949572018181","id":"973715940922687488","lang":"en","in_reply_to_user_id":"442098386","referenced_tweets":[{"type":"replied_to","id":"973713949572018181"}],"geo":{},"attachments":{"media_keys":{}},"Player":"FCHWPO","DateTime":"2018-03-14 20:00:00","GameId":"201803140BOS"},{"entities":{"annotations":{},"mentions":{},"hashtags":{},"urls":[{"start":21,"end":44,"url":"https://t.co/sjer3q1TEU","expanded_url":"https://twitter.com/fchwpo/status/949035976545972227","display_url":"twitter.com/fchwpo/status/…"}]},"source":"Twitter for iPhone","possibly_sensitive":false,"context_annotations":{},"author_id":"1890508795","text":"Let’s go ballers 🏀🏀🏀 https://t.co/sjer3q1TEU","public_metrics":{"retweet_count":0,"reply_count":0,"like_count":1,"quote_count":0},"created_at":"2018-03-13T23:49:53.000Z","conversation_id":"973707754278879232","id":"973707754278879232","lang":"en","referenced_tweets":[{"type":"quoted","id":"949035976545972227"}],"geo":{},"attachments":{"media_keys":{}},"Player":"FCHWPO","DateTime":"2018-03-14 20:00:00","GameId":"201803140BOS"},{"entities":{"annotations":[{"start":29,"end":40,"probability":0.8574,"type":"Person","normalized_text":"Jaylen brown"}],"mentions":[{"start":102,"end":109,"username":"FCHWPO"}],"hashtags":[{"start":88,"end":101,"tag":"celticspride"}],"urls":[{"start":110,"end":133,"url":"https://t.co/1f48JDnrgJ","expanded_url":"https://twitter.com/jdodge13/status/973695863368294400/photo/1","display_url":"pic.twitter.com/1f48JDnrgJ"}]},"source":"Twitter for Android","possibly_sensitive":false,"context_annotations":[{"domain":{"id":"3","name":"TV Shows","description":"Television shows from around the world"},"entity":{"id":"10000607734","name":"NBA Basketball","description":"All the latest basketball action from the NBA."}},{"domain":{"id":"12","name":"Sports Team","description":"A sports team organization, like Arsenal and the Boston Celtics"},"entity":{"id":"706083876595068928","name":"Boston Celtics"}},{"domain":{"id":"26","name":"Sports League","description":""},"entity":{"id":"706083889454813185","name":"NBA"}},{"domain":{"id":"10","name":"Person","description":"Named people in the world like Nelson Mandela"},"entity":{"id":"809849116989632513","name":"Jaylen Brown"}},{"domain":{"id":"60","name":"Athlete","description":"An athlete in the world, like Serena Williams or Lionel Messi"},"entity":{"id":"809849116989632513","name":"Jaylen Brown"}}],"author_id":"368052253","text":"How did I never realize that Jaylen brown actually liked my tweet ABOUT HIM. Much love😍 #celticspride @FCHWPO https://t.co/1f48JDnrgJ","public_metrics":{"retweet_count":0,"reply_count":0,"like_count":7,"quote_count":0},"created_at":"2018-03-13T23:02:38.000Z","conversation_id":"973695863368294400","id":"973695863368294400","lang":"en","referenced_tweets":{},"geo":{},"attachments":{"media_keys":["3_973695848524652544"]},"Player":"FCHWPO","DateTime":"2018-03-14 20:00:00","GameId":"201803140BOS"},{"entities":{"annotations":[{"start":40,"end":45,"probability":0.9723,"type":"Person","normalized_text":"Jaylen"}],"mentions":[{"start":0,"end":7,"username":"FCHWPO"}],"hashtags":{},"urls":{}},"source":"Twitter for iPhone","possibly_sensitive":false,"context_annotations":[{"domain":{"id":"3","name":"TV Shows","description":"Television shows from around the world"},"entity":{"id":"10000607734","name":"NBA Basketball","description":"All the latest basketball action from the NBA."}},{"domain":{"id":"12","name":"Sports Team","description":"A sports team organization, like Arsenal and the Boston Celtics"},"entity":{"id":"706083876595068928","name":"Boston Celtics"}},{"domain":{"id":"26","name":"Sports League","description":""},"entity":{"id":"706083889454813185","name":"NBA"}},{"domain":{"id":"10","name":"Person","description":"Named people in the world like Nelson Mandela"},"entity":{"id":"809849116989632513","name":"Jaylen Brown"}},{"domain":{"id":"60","name":"Athlete","description":"An athlete in the world, like Serena Williams or Lionel Messi"},"entity":{"id":"809849116989632513","name":"Jaylen Brown"}}],"author_id":"105128249","text":"@FCHWPO Hope you can make a return soon Jaylen !! Such a vital piece of the celts team !! Prayers up 🙏🏻","public_metrics":{"retweet_count":0,"reply_count":0,"like_count":0,"quote_count":0},"created_at":"2018-03-13T21:49:36.000Z","conversation_id":"971978189877608454","id":"973677483730993157","lang":"en","in_reply_to_user_id":"419181069","referenced_tweets":[{"type":"replied_to","id":"971978189877608454"}],"geo":{},"attachments":{"media_keys":{}},"Player":"FCHWPO","DateTime":"2018-03-14 20:00:00","GameId":"201803140BOS"},{"entities":{"annotations":{},"mentions":[{"start":1,"end":13,"username":"Kaepernick7"},{"start":14,"end":21,"username":"FCHWPO"},{"start":22,"end":34,"username":"KyrieIrving"}],"hashtags":[{"start":84,"end":101,"tag":"MarchForOurLives"},{"start":102,"end":109,"tag":"Boston"}],"urls":[{"start":110,"end":133,"url":"https://t.co/AQhsuBEYF7","expanded_url":"https://twitter.com/mfolboston/status/973631532194820099","display_url":"twitter.com/mfolboston/sta…"}]},"source":"Twitter for iPhone","possibly_sensitive":false,"context_annotations":[{"domain":{"id":"10","name":"Person","description":"Named people in the world like Nelson Mandela"},"entity":{"id":"783327988611813376","name":"Colin Kaepernick","description":"Colin Kaepernick"}},{"domain":{"id":"60","name":"Athlete","description":"An athlete in the world, like Serena Williams or Lionel Messi"},"entity":{"id":"783327988611813376","name":"Colin Kaepernick","description":"Colin Kaepernick"}},{"domain":{"id":"10","name":"Person","description":"Named people in the world like Nelson Mandela"},"entity":{"id":"809849112870809601","name":"Kyrie Irving"}},{"domain":{"id":"10","name":"Person","description":"Named people in the world like Nelson Mandela"},"entity":{"id":"809849116989632513","name":"Jaylen Brown"}},{"domain":{"id":"60","name":"Athlete","description":"An athlete in the world, like Serena Williams or Lionel Messi"},"entity":{"id":"809849112870809601","name":"Kyrie Irving"}},{"domain":{"id":"60","name":"Athlete","description":"An athlete in the world, like Serena Williams or Lionel Messi"},"entity":{"id":"809849116989632513","name":"Jaylen Brown"}}],"author_id":"806871234642345984","text":".@Kaepernick7 @FCHWPO @KyrieIrving - would love to see you guys share this message. #MarchForOurLives #Boston https://t.co/AQhsuBEYF7","public_metrics":{"retweet_count":0,"reply_count":0,"like_count":1,"quote_count":0},"created_at":"2018-03-13T19:16:52.000Z","conversation_id":"973639046927876096","id":"973639046927876096","lang":"en","referenced_tweets":[{"type":"quoted","id":"973631532194820099"}],"geo":{},"attachments":{"media_keys":{}},"Player":"FCHWPO","DateTime":"2018-03-14 20:00:00","GameId":"201803140BOS"},{"entities":{"annotations":{},"mentions":[{"start":0,"end":7,"username":"FCHWPO"},{"start":93,"end":100,"username":"FCHWPO"},{"start":101,"end":111,"username":"smart_MS3"}],"hashtags":{},"urls":{}},"source":"Twitter for iPhone","possibly_sensitive":false,"context_annotations":[{"domain":{"id":"10","name":"Person","description":"Named people in the world like Nelson Mandela"},"entity":{"id":"809849108659773440","name":"Marcus Smart"}},{"domain":{"id":"10","name":"Person","description":"Named people in the world like Nelson Mandela"},"entity":{"id":"809849116989632513","name":"Jaylen Brown"}},{"domain":{"id":"60","name":"Athlete","description":"An athlete in the world, like Serena Williams or Lionel Messi"},"entity":{"id":"809849108659773440","name":"Marcus Smart"}},{"domain":{"id":"60","name":"Athlete","description":"An athlete in the world, like Serena Williams or Lionel Messi"},"entity":{"id":"809849116989632513","name":"Jaylen Brown"}}],"author_id":"972079698804133889","text":"@FCHWPO If you hate on smart you don't watch every game...he changes everything!!! Much Love @FCHWPO @smart_MS3","public_metrics":{"retweet_count":0,"reply_count":0,"like_count":1,"quote_count":0},"created_at":"2018-03-13T13:55:17.000Z","conversation_id":"970886697130119170","id":"973558116741771264","lang":"en","in_reply_to_user_id":"419181069","referenced_tweets":[{"type":"replied_to","id":"970886697130119170"}],"geo":{},"attachments":{"media_keys":{}},"Player":"FCHWPO","DateTime":"2018-03-14 20:00:00","GameId":"201803140BOS"},{"entities":{"annotations":{},"mentions":[{"start":0,"end":7,"username":"FCHWPO"}],"hashtags":{},"urls":{}},"source":"Twitter for Android","possibly_sensitive":false,"context_annotations":[{"domain":{"id":"10","name":"Person","description":"Named people in the world like Nelson Mandela"},"entity":{"id":"809849116989632513","name":"Jaylen Brown"}},{"domain":{"id":"60","name":"Athlete","description":"An athlete in the world, like Serena Williams or Lionel Messi"},"entity":{"id":"809849116989632513","name":"Jaylen Brown"}}],"author_id":"4253363297","text":"@FCHWPO Strong dude 💯✊","public_metrics":{"retweet_count":0,"reply_count":0,"like_count":0,"quote_count":0},"created_at":"2018-03-13T12:52:04.000Z","conversation_id":"971978189877608454","id":"973542207046258689","lang":"en","in_reply_to_user_id":"419181069","referenced_tweets":[{"type":"replied_to","id":"971978189877608454"}],"geo":{},"attachments":{"media_keys":{}},"Player":"FCHWPO","DateTime":"2018-03-14 20:00:00","GameId":"201803140BOS"},{"entities":{"annotations":{},"mentions":[{"start":18,"end":26,"username":"celtics"},{"start":30,"end":37,"username":"FCHWPO"}],"hashtags":{},"urls":[{"start":118,"end":141,"url":"https://t.co/bAZ1SCbJBc","expanded_url":"https://twitter.com/allworldathlete/status/973434975528747008/video/1","display_url":"pic.twitter.com/bAZ1SCbJBc"}]},"source":"Twitter Web Client","possibly_sensitive":false,"context_annotations":[{"domain":{"id":"3","name":"TV Shows","description":"Television shows from around the world"},"entity":{"id":"10000607734","name":"NBA Basketball","description":"All the latest basketball action from the NBA."}},{"domain":{"id":"3","name":"TV Shows","description":"Television shows from around the world"},"entity":{"id":"10029190505","name":"Live: NBA Basketball","description":"Live coverage from the National Basketball Association, the top basketball league in North America."}},{"domain":{"id":"3","name":"TV Shows","description":"Television shows from around the world"},"entity":{"id":"10029304530","name":"NBA Basketball"}},{"domain":{"id":"12","name":"Sports Team","description":"A sports team organization, like Arsenal and the Boston Celtics"},"entity":{"id":"706083876595068928","name":"Boston Celtics"}},{"domain":{"id":"26","name":"Sports League","description":""},"entity":{"id":"706083889454813185","name":"NBA"}},{"domain":{"id":"10","name":"Person","description":"Named people in the world like Nelson Mandela"},"entity":{"id":"809849116989632513","name":"Jaylen Brown"}},{"domain":{"id":"60","name":"Athlete","description":"An athlete in the world, like Serena Williams or Lionel Messi"},"entity":{"id":"809849116989632513","name":"Jaylen Brown"}}],"author_id":"973346834830766080","text":"Prayers go out to @celtics SF @FCHWPO , Great Dunk but horrible landing there. Great talent future is bright for him. https://t.co/bAZ1SCbJBc","public_metrics":{"retweet_count":0,"reply_count":0,"like_count":0,"quote_count":0},"created_at":"2018-03-13T05:45:58.000Z","conversation_id":"973434975528747008","id":"973434975528747008","lang":"en","referenced_tweets":{},"geo":{},"attachments":{"media_keys":["7_973434687132614656"]},"Player":"FCHWPO","DateTime":"2018-03-14 20:00:00","GameId":"201803140BOS"},{"entities":{"annotations":{},"mentions":[{"start":0,"end":9,"username":"paulfang"},{"start":10,"end":17,"username":"FCHWPO"}],"hashtags":{},"urls":{}},"source":"Twitter Web Client","possibly_sensitive":false,"context_annotations":[{"domain":{"id":"10","name":"Person","description":"Named people in the world like Nelson Mandela"},"entity":{"id":"809849116989632513","name":"Jaylen Brown"}},{"domain":{"id":"60","name":"Athlete","description":"An athlete in the world, like Serena Williams or Lionel Messi"},"entity":{"id":"809849116989632513","name":"Jaylen Brown"}}],"author_id":"22411155","text":"@paulfang @FCHWPO On the real, they need him","public_metrics":{"retweet_count":0,"reply_count":0,"like_count":1,"quote_count":0},"created_at":"2018-03-13T05:39:48.000Z","conversation_id":"973204336544120833","id":"973433424185667584","lang":"en","in_reply_to_user_id":"90092937","referenced_tweets":[{"type":"replied_to","id":"973416535174742016"}],"geo":{},"attachments":{"media_keys":{}},"Player":"FCHWPO","DateTime":"2018-03-14 20:00:00","GameId":"201803140BOS"},{"entities":{"annotations":{},"mentions":[{"start":24,"end":32,"username":"celtics"},{"start":53,"end":60,"username":"FCHWPO"}],"hashtags":{},"urls":{}},"source":"Twitter Web App","possibly_sensitive":false,"context_annotations":[{"domain":{"id":"3","name":"TV Shows","description":"Television shows from around the world"},"entity":{"id":"10000607734","name":"NBA Basketball","description":"All the latest basketball action from the NBA."}},{"domain":{"id":"3","name":"TV Shows","description":"Television shows from around the world"},"entity":{"id":"10029190505","name":"Live: NBA Basketball","description":"Live coverage from the National Basketball Association, the top basketball league in North America."}},{"domain":{"id":"3","name":"TV Shows","description":"Television shows from around the world"},"entity":{"id":"10029304530","name":"NBA Basketball"}},{"domain":{"id":"12","name":"Sports Team","description":"A sports team organization, like Arsenal and the Boston Celtics"},"entity":{"id":"706083876595068928","name":"Boston Celtics"}},{"domain":{"id":"26","name":"Sports League","description":""},"entity":{"id":"706083889454813185","name":"NBA"}},{"domain":{"id":"10","name":"Person","description":"Named people in the world like Nelson Mandela"},"entity":{"id":"809849116989632513","name":"Jaylen Brown"}},{"domain":{"id":"60","name":"Athlete","description":"An athlete in the world, like Serena Williams or Lionel Messi"},"entity":{"id":"809849116989632513","name":"Jaylen Brown"}}],"author_id":"753187516887527424","text":"GOD BLESS YOU BELOVED!! @CELTICS🍀\nHOW IS OUR BROTHER @FCHWPO I AM BELIEVING THAT HE IS OK!! I KNOW IT MIGHT SEEM  PRIVATE, BUT WE NEED UPDATES AND KNOWLEDGE OF THE PROCESS!! 💒💞👍📖👆🌹🌺💓💖💝🌼🌸🌸🌼💝💖💓💕🌹🌺💞💒🌸🌼💝💖💓","public_metrics":{"retweet_count":0,"reply_count":0,"like_count":0,"quote_count":0},"created_at":"2018-03-13T03:35:18.000Z","conversation_id":"973402090868363265","id":"973402090868363265","lang":"en","referenced_tweets":{},"geo":{},"attachments":{"media_keys":{}},"Player":"FCHWPO","DateTime":"2018-03-14 20:00:00","GameId":"201803140BOS"},{"entities":{"annotations":[{"start":71,"end":76,"probability":0.7783,"type":"Person","normalized_text":"jaylen"},{"start":96,"end":106,"probability":0.4857,"type":"Place","normalized_text":"boston city"}],"mentions":[{"start":28,"end":35,"username":"FCHWPO"},{"start":36,"end":46,"username":"jaytatum0"}],"hashtags":{},"urls":{}},"source":"Twitter for iPhone","possibly_sensitive":false,"context_annotations":[{"domain":{"id":"10","name":"Person","description":"Named people in the world like Nelson Mandela"},"entity":{"id":"809849116989632513","name":"Jaylen Brown"}},{"domain":{"id":"10","name":"Person","description":"Named people in the world like Nelson Mandela"},"entity":{"id":"831260175956783105","name":"Jayson Tatum","description":"Jayson Tatum"}},{"domain":{"id":"60","name":"Athlete","description":"An athlete in the world, like Serena Williams or Lionel Messi"},"entity":{"id":"809849116989632513","name":"Jaylen Brown"}},{"domain":{"id":"60","name":"Athlete","description":"An athlete in the world, like Serena Williams or Lionel Messi"},"entity":{"id":"831260175956783105","name":"Jayson Tatum","description":"Jayson Tatum"}}],"author_id":"198106548","text":"You came to my dream bruhhh @FCHWPO @jaytatum0 , we ride together with jaylen’s car through the boston city. Haha so weird","public_metrics":{"retweet_count":0,"reply_count":0,"like_count":0,"quote_count":0},"created_at":"2018-03-13T01:36:17.000Z","conversation_id":"973372141981724672","id":"973372141981724672","lang":"en","referenced_tweets":{},"geo":{},"attachments":{"media_keys":{}},"Player":"FCHWPO","DateTime":"2018-03-14 20:00:00","GameId":"201803140BOS"},{"entities":{"annotations":{},"mentions":[{"start":79,"end":86,"username":"FCHWPO"},{"start":87,"end":97,"username":"smart_MS3"},{"start":98,"end":107,"username":"dtheis10"},{"start":108,"end":120,"username":"KyrieIrving"},{"start":121,"end":132,"username":"Al_Horford"},{"start":149,"end":163,"username":"gordonhayward"}],"hashtags":{},"urls":{}},"source":"TweetCaster for Android","possibly_sensitive":false,"context_annotations":[{"domain":{"id":"10","name":"Person","description":"Named people in the world like Nelson Mandela"},"entity":{"id":"809849107590180865","name":"Al Horford"}},{"domain":{"id":"10","name":"Person","description":"Named people in the world like Nelson Mandela"},"entity":{"id":"912907093786497024","name":"Daniel Theis"}},{"domain":{"id":"60","name":"Athlete","description":"An athlete in the world, like Serena Williams or Lionel Messi"},"entity":{"id":"809849107590180865","name":"Al Horford"}},{"domain":{"id":"60","name":"Athlete","description":"An athlete in the world, like Serena Williams or Lionel Messi"},"entity":{"id":"912907093786497024","name":"Daniel Theis"}},{"domain":{"id":"10","name":"Person","description":"Named people in the world like Nelson Mandela"},"entity":{"id":"809849108659773440","name":"Marcus Smart"}},{"domain":{"id":"10","name":"Person","description":"Named people in the world like Nelson Mandela"},"entity":{"id":"809849112870809601","name":"Kyrie Irving"}},{"domain":{"id":"10","name":"Person","description":"Named people in the world like Nelson Mandela"},"entity":{"id":"809849115597078530","name":"Gordon Hayward"}},{"domain":{"id":"10","name":"Person","description":"Named people in the world like Nelson Mandela"},"entity":{"id":"809849116989632513","name":"Jaylen Brown"}},{"domain":{"id":"60","name":"Athlete","description":"An athlete in the world, like Serena Williams or Lionel Messi"},"entity":{"id":"809849108659773440","name":"Marcus Smart"}},{"domain":{"id":"60","name":"Athlete","description":"An athlete in the world, like Serena Williams or Lionel Messi"},"entity":{"id":"809849112870809601","name":"Kyrie Irving"}},{"domain":{"id":"60","name":"Athlete","description":"An athlete in the world, like Serena Williams or Lionel Messi"},"entity":{"id":"809849115597078530","name":"Gordon Hayward"}},{"domain":{"id":"60","name":"Athlete","description":"An athlete in the world, like Serena Williams or Lionel Messi"},"entity":{"id":"809849116989632513","name":"Jaylen Brown"}}],"author_id":"138163489","text":"Wow, wishing you all a speedy recovery...So, prayers up for My Boyzzzzzzz!! 🙏🙏 @FCHWPO @smart_MS3 @dtheis10 @KyrieIrving @Al_Horford &amp; of course @gordonhayward","public_metrics":{"retweet_count":0,"reply_count":0,"like_count":0,"quote_count":0},"created_at":"2018-03-13T01:17:34.000Z","conversation_id":"973367429538689024","id":"973367429538689024","lang":"en","referenced_tweets":{},"geo":{},"attachments":{"media_keys":{}},"Player":"FCHWPO","DateTime":"2018-03-14 20:00:00","GameId":"201803140BOS"},{"entities":{"annotations":{},"mentions":[{"start":27,"end":34,"username":"FCHWPO"}],"hashtags":{},"urls":{}},"source":"Twitter Web Client","possibly_sensitive":false,"context_annotations":[{"domain":{"id":"10","name":"Person","description":"Named people in the world like Nelson Mandela"},"entity":{"id":"809849116989632513","name":"Jaylen Brown"}},{"domain":{"id":"60","name":"Athlete","description":"An athlete in the world, like Serena Williams or Lionel Messi"},"entity":{"id":"809849116989632513","name":"Jaylen Brown"}}],"author_id":"787682711230119936","text":"ready for that playoff run @FCHWPO yeah im going to be talking trash if you all dont make it out of the first round or second round....have to decide...","public_metrics":{"retweet_count":0,"reply_count":0,"like_count":0,"quote_count":0},"created_at":"2018-03-12T21:55:19.000Z","conversation_id":"973316531659640838","id":"973316531659640838","lang":"en","referenced_tweets":{},"geo":{},"attachments":{"media_keys":{}},"Player":"FCHWPO","DateTime":"2018-03-14 20:00:00","GameId":"201803140BOS"},{"entities":{"annotations":[{"start":36,"end":42,"probability":0.687,"type":"Place","normalized_text":"Toronto"},{"start":122,"end":128,"probability":0.5001,"type":"Person","normalized_text":"Cavs-Cs"}],"mentions":[{"start":0,"end":16,"username":"CharlieBucket44"},{"start":17,"end":24,"username":"FCHWPO"},{"start":25,"end":35,"username":"jaytatum0"}],"hashtags":{},"urls":{}},"source":"Twitter for iPhone","possibly_sensitive":false,"context_annotations":[{"domain":{"id":"3","name":"TV Shows","description":"Television shows from around the world"},"entity":{"id":"10000607734","name":"NBA Basketball","description":"All the latest basketball action from the NBA."}},{"domain":{"id":"12","name":"Sports Team","description":"A sports team organization, like Arsenal and the Boston Celtics"},"entity":{"id":"706083865589198850","name":"Cleveland Cavaliers"}},{"domain":{"id":"26","name":"Sports League","description":""},"entity":{"id":"706083889454813185","name":"NBA"}},{"domain":{"id":"10","name":"Person","description":"Named people in the world like Nelson Mandela"},"entity":{"id":"809849116989632513","name":"Jaylen Brown"}},{"domain":{"id":"10","name":"Person","description":"Named people in the world like Nelson Mandela"},"entity":{"id":"831260175956783105","name":"Jayson Tatum","description":"Jayson Tatum"}},{"domain":{"id":"60","name":"Athlete","description":"An athlete in the world, like Serena Williams or Lionel Messi"},"entity":{"id":"809849116989632513","name":"Jaylen Brown"}},{"domain":{"id":"60","name":"Athlete","description":"An athlete in the world, like Serena Williams or Lionel Messi"},"entity":{"id":"831260175956783105","name":"Jayson Tatum","description":"Jayson Tatum"}}],"author_id":"374205913","text":"@CharlieBucket44 @FCHWPO @jaytatum0 Toronto disappears in the playoffs. If seeding works out in our favor I can still see Cavs-Cs in the ecf","public_metrics":{"retweet_count":0,"reply_count":0,"like_count":0,"quote_count":0},"created_at":"2018-03-12T20:44:05.000Z","conversation_id":"973281840504229888","id":"973298605661581312","lang":"en","in_reply_to_user_id":"632091772","referenced_tweets":[{"type":"replied_to","id":"973295365041553408"}],"geo":{},"attachments":{"media_keys":{}},"Player":"FCHWPO","DateTime":"2018-03-14 20:00:00","GameId":"201803140BOS"},{"entities":{"annotations":{},"mentions":[{"start":93,"end":100,"username":"FCHWPO"},{"start":107,"end":117,"username":"jaytatum0"}],"hashtags":{},"urls":{}},"source":"Twitter for Android","possibly_sensitive":false,"context_annotations":[{"domain":{"id":"10","name":"Person","description":"Named people in the world like Nelson Mandela"},"entity":{"id":"809849116989632513","name":"Jaylen Brown"}},{"domain":{"id":"10","name":"Person","description":"Named people in the world like Nelson Mandela"},"entity":{"id":"831260175956783105","name":"Jayson Tatum","description":"Jayson Tatum"}},{"domain":{"id":"60","name":"Athlete","description":"An athlete in the world, like Serena Williams or Lionel Messi"},"entity":{"id":"809849116989632513","name":"Jaylen Brown"}},{"domain":{"id":"60","name":"Athlete","description":"An athlete in the world, like Serena Williams or Lionel Messi"},"entity":{"id":"831260175956783105","name":"Jayson Tatum","description":"Jayson Tatum"}}],"author_id":"632091772","text":"@joejurevicious I have 0 playoff expectations. It was a successful year for the future studs @FCHWPO &amp; @jaytatum0","public_metrics":{"retweet_count":0,"reply_count":1,"like_count":0,"quote_count":0},"created_at":"2018-03-12T20:31:12.000Z","conversation_id":"973281840504229888","id":"973295365041553408","lang":"en","in_reply_to_user_id":"374205913","referenced_tweets":[{"type":"replied_to","id":"973285952033640449"}],"geo":{},"attachments":{"media_keys":{}},"Player":"FCHWPO","DateTime":"2018-03-14 20:00:00","GameId":"201803140BOS"},{"entities":{"annotations":{},"mentions":[{"start":0,"end":7,"username":"FCHWPO"}],"hashtags":{},"urls":{}},"source":"Twitter for iPhone","possibly_sensitive":false,"context_annotations":[{"domain":{"id":"10","name":"Person","description":"Named people in the world like Nelson Mandela"},"entity":{"id":"809849116989632513","name":"Jaylen Brown"}},{"domain":{"id":"60","name":"Athlete","description":"An athlete in the world, like Serena Williams or Lionel Messi"},"entity":{"id":"809849116989632513","name":"Jaylen Brown"}}],"author_id":"841869771666792448","text":"@FCHWPO you got a new nickname yet? I’m about to make a jacket with your jersey","public_metrics":{"retweet_count":0,"reply_count":0,"like_count":0,"quote_count":0},"created_at":"2018-03-12T20:07:26.000Z","conversation_id":"973289385046155264","id":"973289385046155264","lang":"en","in_reply_to_user_id":"419181069","referenced_tweets":{},"geo":{},"attachments":{"media_keys":{}},"Player":"FCHWPO","DateTime":"2018-03-14 20:00:00","GameId":"201803140BOS"}]
